<?xml version="1.0" ?>
<annotation>
    <filename>文献通考_三百四十八卷_元_马端临撰_明嘉靖三年司礼监刊本_哈佛大学图书馆藏_黑白版_08720.jpg</filename>
    <source/>
    <size>
        <width>2170</width>
        <height>4142</height>
        <depth>3</depth>
    </size>
    <segmented>0</segmented>
    <object>
        <name>中</name>
        <pose>Unspecified</pose>
        <truncated>0</truncated>
        <difficult>0</difficult>
        <bndbox>
            <xmin>1909</xmin>
            <ymin>821</ymin>
            <xmax>2049</xmax>
            <ymax>974</ymax>
        </bndbox>
    </object>
    <object>
        <name>五</name>
        <pose>Unspecified</pose>
        <truncated>0</truncated>
        <difficult>0</difficult>
        <bndbox>
            <xmin>1892</xmin>
            <ymin>983</ymin>
            <xmax>2053</xmax>
            <ymax>1100</ymax>
        </bndbox>
    </object>
    <object>
        <name>十</name>
        <pose>Unspecified</pose>
        <truncated>0</truncated>
        <difficult>0</difficult>
        <bndbox>
            <xmin>1889</xmin>
            <ymin>1111</ymin>
            <xmax>2038</xmax>
            <ymax>1251</ymax>
        </bndbox>
    </object>
    <object>
        <name>之</name>
        <pose>Unspecified</pose>
        <truncated>0</truncated>
        <difficult>0</difficult>
        <bndbox>
            <xmin>1884</xmin>
            <ymin>1261</ymin>
            <xmax>2035</xmax>
            <ymax>1385</ymax>
        </bndbox>
    </object>
    <object>
        <name>數</name>
        <pose>Unspecified</pose>
        <truncated>0</truncated>
        <difficult>0</difficult>
        <bndbox>
            <xmin>1884</xmin>
            <ymin>1395</ymin>
            <xmax>2041</xmax>
            <ymax>1541</ymax>
        </bndbox>
    </object>
    <object>
        <name>禁</name>
        <pose>Unspecified</pose>
        <truncated>0</truncated>
        <difficult>0</difficult>
        <bndbox>
            <xmin>1881</xmin>
            <ymin>1538</ymin>
            <xmax>2031</xmax>
            <ymax>1710</ymax>
        </bndbox>
    </object>
    <object>
        <name>昭</name>
        <pose>Unspecified</pose>
        <truncated>0</truncated>
        <difficult>0</difficult>
        <bndbox>
            <xmin>1880</xmin>
            <ymin>1717</ymin>
            <xmax>2028</xmax>
            <ymax>1840</ymax>
        </bndbox>
    </object>
    <object>
        <name>陵</name>
        <pose>Unspecified</pose>
        <truncated>0</truncated>
        <difficult>0</difficult>
        <bndbox>
            <xmin>1879</xmin>
            <ymin>1843</ymin>
            <xmax>2029</xmax>
            <ymax>1996</ymax>
        </bndbox>
    </object>
    <object>
        <name>東</name>
        <pose>Unspecified</pose>
        <truncated>0</truncated>
        <difficult>0</difficult>
        <bndbox>
            <xmin>1876</xmin>
            <ymin>1996</ymin>
            <xmax>2030</xmax>
            <ymax>2141</ymax>
        </bndbox>
    </object>
    <object>
        <name>北</name>
        <pose>Unspecified</pose>
        <truncated>0</truncated>
        <difficult>0</difficult>
        <bndbox>
            <xmin>1871</xmin>
            <ymin>2149</ymin>
            <xmax>2022</xmax>
            <ymax>2277</ymax>
        </bndbox>
    </object>
    <object>
        <name>山</name>
        <pose>Unspecified</pose>
        <truncated>0</truncated>
        <difficult>0</difficult>
        <bndbox>
            <xmin>1873</xmin>
            <ymin>2297</ymin>
            <xmax>2007</xmax>
            <ymax>2420</ymax>
        </bndbox>
    </object>
    <object>
        <name>口</name>
        <pose>Unspecified</pose>
        <truncated>0</truncated>
        <difficult>0</difficult>
        <bndbox>
            <xmin>1877</xmin>
            <ymin>2457</ymin>
            <xmax>1995</xmax>
            <ymax>2550</ymax>
        </bndbox>
    </object>
    <object>
        <name>路</name>
        <pose>Unspecified</pose>
        <truncated>0</truncated>
        <difficult>0</difficult>
        <bndbox>
            <xmin>1853</xmin>
            <ymin>2577</ymin>
            <xmax>2012</xmax>
            <ymax>2718</ymax>
        </bndbox>
    </object>
    <object>
        <name>勿</name>
        <pose>Unspecified</pose>
        <truncated>0</truncated>
        <difficult>0</difficult>
        <bndbox>
            <xmin>1862</xmin>
            <ymin>2724</ymin>
            <xmax>2000</xmax>
            <ymax>2863</ymax>
        </bndbox>
    </object>
    <object>
        <name>耕</name>
        <pose>Unspecified</pose>
        <truncated>0</truncated>
        <difficult>0</difficult>
        <bndbox>
            <xmin>1857</xmin>
            <ymin>2865</ymin>
            <xmax>2013</xmax>
            <ymax>3011</ymax>
        </bndbox>
    </object>
    <object>
        <name>鑿</name>
        <pose>Unspecified</pose>
        <truncated>0</truncated>
        <difficult>0</difficult>
        <bndbox>
            <xmin>1856</xmin>
            <ymin>3016</ymin>
            <xmax>2019</xmax>
            <ymax>3189</ymax>
        </bndbox>
    </object>
    <object>
        <name>中</name>
        <pose>Unspecified</pose>
        <truncated>0</truncated>
        <difficult>0</difficult>
        <bndbox>
            <xmin>1852</xmin>
            <ymin>3186</ymin>
            <xmax>1994</xmax>
            <ymax>3332</ymax>
        </bndbox>
    </object>
    <object>
        <name>有</name>
        <pose>Unspecified</pose>
        <truncated>0</truncated>
        <difficult>0</difficult>
        <bndbox>
            <xmin>1837</xmin>
            <ymin>3323</ymin>
            <xmax>1991</xmax>
            <ymax>3454</ymax>
        </bndbox>
    </object>
    <object>
        <name>民</name>
        <pose>Unspecified</pose>
        <truncated>0</truncated>
        <difficult>0</difficult>
        <bndbox>
            <xmin>1839</xmin>
            <ymin>3457</ymin>
            <xmax>1994</xmax>
            <ymax>3601</ymax>
        </bndbox>
    </object>
    <object>
        <name>田</name>
        <pose>Unspecified</pose>
        <truncated>0</truncated>
        <difficult>0</difficult>
        <bndbox>
            <xmin>1845</xmin>
            <ymin>3614</ymin>
            <xmax>1980</xmax>
            <ymax>3726</ymax>
        </bndbox>
    </object>
    <object>
        <name>則</name>
        <pose>Unspecified</pose>
        <truncated>0</truncated>
        <difficult>0</difficult>
        <bndbox>
            <xmin>1694</xmin>
            <ymin>822</ymin>
            <xmax>1842</xmax>
            <ymax>967</ymax>
        </bndbox>
    </object>
    <object>
        <name>給</name>
        <pose>Unspecified</pose>
        <truncated>0</truncated>
        <difficult>0</difficult>
        <bndbox>
            <xmin>1692</xmin>
            <ymin>970</ymin>
            <xmax>1864</xmax>
            <ymax>1109</ymax>
        </bndbox>
    </object>
    <object>
        <name>其</name>
        <pose>Unspecified</pose>
        <truncated>0</truncated>
        <difficult>0</difficult>
        <bndbox>
            <xmin>1681</xmin>
            <ymin>1110</ymin>
            <xmax>1849</xmax>
            <ymax>1256</ymax>
        </bndbox>
    </object>
    <object>
        <name>直</name>
        <pose>Unspecified</pose>
        <truncated>0</truncated>
        <difficult>0</difficult>
        <bndbox>
            <xmin>1674</xmin>
            <ymin>1252</ymin>
            <xmax>1844</xmax>
            <ymax>1390</ymax>
        </bndbox>
    </object>
    <object>
        <name>或</name>
        <pose>Unspecified</pose>
        <truncated>0</truncated>
        <difficult>0</difficult>
        <bndbox>
            <xmin>1689</xmin>
            <ymin>1390</ymin>
            <xmax>1831</xmax>
            <ymax>1535</ymax>
        </bndbox>
    </object>
    <object>
        <name>易</name>
        <pose>Unspecified</pose>
        <truncated>0</truncated>
        <difficult>0</difficult>
        <bndbox>
            <xmin>1674</xmin>
            <ymin>1539</ymin>
            <xmax>1817</xmax>
            <ymax>1705</ymax>
        </bndbox>
    </object>
    <object>
        <name>以</name>
        <pose>Unspecified</pose>
        <truncated>0</truncated>
        <difficult>0</difficult>
        <bndbox>
            <xmin>1680</xmin>
            <ymin>1715</ymin>
            <xmax>1821</xmax>
            <ymax>1834</ymax>
        </bndbox>
    </object>
    <object>
        <name>官</name>
        <pose>Unspecified</pose>
        <truncated>0</truncated>
        <difficult>0</difficult>
        <bndbox>
            <xmin>1678</xmin>
            <ymin>1847</ymin>
            <xmax>1820</xmax>
            <ymax>1994</ymax>
        </bndbox>
    </object>
    <object>
        <name>地</name>
        <pose>Unspecified</pose>
        <truncated>0</truncated>
        <difficult>0</difficult>
        <bndbox>
            <xmin>1667</xmin>
            <ymin>1997</ymin>
            <xmax>1815</xmax>
            <ymax>2121</ymax>
        </bndbox>
    </object>
    <object>
        <name>舊</name>
        <pose>Unspecified</pose>
        <truncated>0</truncated>
        <difficult>0</difficult>
        <bndbox>
            <xmin>1670</xmin>
            <ymin>2127</ymin>
            <xmax>1806</xmax>
            <ymax>2300</ymax>
        </bndbox>
    </object>
    <object>
        <name>以</name>
        <pose>Unspecified</pose>
        <truncated>0</truncated>
        <difficult>0</difficult>
        <bndbox>
            <xmin>1661</xmin>
            <ymin>2307</ymin>
            <xmax>1812</xmax>
            <ymax>2417</ymax>
        </bndbox>
    </object>
    <object>
        <name>兆</name>
        <pose>Unspecified</pose>
        <truncated>0</truncated>
        <difficult>0</difficult>
        <bndbox>
            <xmin>1655</xmin>
            <ymin>2433</ymin>
            <xmax>1819</xmax>
            <ymax>2569</ymax>
        </bndbox>
    </object>
    <object>
        <name>域</name>
        <pose>Unspecified</pose>
        <truncated>0</truncated>
        <difficult>0</difficult>
        <bndbox>
            <xmin>1654</xmin>
            <ymin>2573</ymin>
            <xmax>1821</xmax>
            <ymax>2717</ymax>
        </bndbox>
    </object>
    <object>
        <name>南</name>
        <pose>Unspecified</pose>
        <truncated>0</truncated>
        <difficult>0</difficult>
        <bndbox>
            <xmin>1662</xmin>
            <ymin>2718</ymin>
            <xmax>1807</xmax>
            <ymax>2862</ymax>
        </bndbox>
    </object>
    <object>
        <name>地</name>
        <pose>Unspecified</pose>
        <truncated>0</truncated>
        <difficult>0</difficult>
        <bndbox>
            <xmin>1659</xmin>
            <ymin>2869</ymin>
            <xmax>1816</xmax>
            <ymax>2993</ymax>
        </bndbox>
    </object>
    <object>
        <name>十</name>
        <pose>Unspecified</pose>
        <truncated>0</truncated>
        <difficult>0</difficult>
        <bndbox>
            <xmin>1653</xmin>
            <ymin>3015</ymin>
            <xmax>1802</xmax>
            <ymax>3166</ymax>
        </bndbox>
    </object>
    <object>
        <name>頃</name>
        <pose>Unspecified</pose>
        <truncated>0</truncated>
        <difficult>0</difficult>
        <bndbox>
            <xmin>1648</xmin>
            <ymin>3172</ymin>
            <xmax>1799</xmax>
            <ymax>3313</ymax>
        </bndbox>
    </object>
    <object>
        <name>有</name>
        <pose>Unspecified</pose>
        <truncated>0</truncated>
        <difficult>0</difficult>
        <bndbox>
            <xmin>1650</xmin>
            <ymin>3318</ymin>
            <xmax>1796</xmax>
            <ymax>3453</ymax>
        </bndbox>
    </object>
    <object>
        <name>畸</name>
        <pose>Unspecified</pose>
        <truncated>0</truncated>
        <difficult>0</difficult>
        <bndbox>
            <xmin>1646</xmin>
            <ymin>3455</ymin>
            <xmax>1798</xmax>
            <ymax>3602</ymax>
        </bndbox>
    </object>
    <object>
        <name>資</name>
        <pose>Unspecified</pose>
        <truncated>0</truncated>
        <difficult>0</difficult>
        <bndbox>
            <xmin>1656</xmin>
            <ymin>3602</ymin>
            <xmax>1791</xmax>
            <ymax>3749</ymax>
        </bndbox>
    </object>
    <object>
        <name>官</name>
        <pose>Unspecified</pose>
        <truncated>0</truncated>
        <difficult>0</difficult>
        <bndbox>
            <xmin>1492</xmin>
            <ymin>809</ymin>
            <xmax>1650</xmax>
            <ymax>960</ymax>
        </bndbox>
    </object>
    <object>
        <name>費</name>
        <pose>Unspecified</pose>
        <truncated>0</truncated>
        <difficult>0</difficult>
        <bndbox>
            <xmin>1495</xmin>
            <ymin>963</ymin>
            <xmax>1649</xmax>
            <ymax>1131</ymax>
        </bndbox>
    </object>
    <object>
        <name>而</name>
        <pose>Unspecified</pose>
        <truncated>0</truncated>
        <difficult>0</difficult>
        <bndbox>
            <xmin>1490</xmin>
            <ymin>1130</ymin>
            <xmax>1638</xmax>
            <ymax>1245</ymax>
        </bndbox>
    </object>
    <object>
        <name>監</name>
        <pose>Unspecified</pose>
        <truncated>0</truncated>
        <difficult>0</difficult>
        <bndbox>
            <xmin>1484</xmin>
            <ymin>1247</ymin>
            <xmax>1633</xmax>
            <ymax>1396</ymax>
        </bndbox>
    </object>
    <object>
        <name>護</name>
        <pose>Unspecified</pose>
        <truncated>0</truncated>
        <difficult>0</difficult>
        <bndbox>
            <xmin>1482</xmin>
            <ymin>1399</ymin>
            <xmax>1637</xmax>
            <ymax>1544</ymax>
        </bndbox>
    </object>
    <object>
        <name>官</name>
        <pose>Unspecified</pose>
        <truncated>0</truncated>
        <difficult>0</difficult>
        <bndbox>
            <xmin>1483</xmin>
            <ymin>1548</ymin>
            <xmax>1626</xmax>
            <ymax>1688</ymax>
        </bndbox>
    </object>
    <object>
        <name>循</name>
        <pose>Unspecified</pose>
        <truncated>0</truncated>
        <difficult>0</difficult>
        <bndbox>
            <xmin>1480</xmin>
            <ymin>1696</ymin>
            <xmax>1623</xmax>
            <ymax>1842</ymax>
        </bndbox>
    </object>
    <object>
        <name>習</name>
        <pose>Unspecified</pose>
        <truncated>0</truncated>
        <difficult>0</difficult>
        <bndbox>
            <xmin>1478</xmin>
            <ymin>1850</ymin>
            <xmax>1607</xmax>
            <ymax>1999</ymax>
        </bndbox>
    </object>
    <object>
        <name>以</name>
        <pose>Unspecified</pose>
        <truncated>0</truncated>
        <difficult>0</difficult>
        <bndbox>
            <xmin>1464</xmin>
            <ymin>2009</ymin>
            <xmax>1612</xmax>
            <ymax>2123</ymax>
        </bndbox>
    </object>
    <object>
        <name>為</name>
        <pose>Unspecified</pose>
        <truncated>0</truncated>
        <difficult>0</difficult>
        <bndbox>
            <xmin>1474</xmin>
            <ymin>2135</ymin>
            <xmax>1616</xmax>
            <ymax>2291</ymax>
        </bndbox>
    </object>
    <object>
        <name>圭</name>
        <pose>Unspecified</pose>
        <truncated>0</truncated>
        <difficult>0</difficult>
        <bndbox>
            <xmin>1464</xmin>
            <ymin>2290</ymin>
            <xmax>1616</xmax>
            <ymax>2426</ymax>
        </bndbox>
    </object>
    <object>
        <name>田</name>
        <pose>Unspecified</pose>
        <truncated>0</truncated>
        <difficult>0</difficult>
        <bndbox>
            <xmin>1467</xmin>
            <ymin>2444</ymin>
            <xmax>1611</xmax>
            <ymax>2564</ymax>
        </bndbox>
    </object>
    <object>
        <name>帝</name>
        <pose>Unspecified</pose>
        <truncated>0</truncated>
        <difficult>0</difficult>
        <bndbox>
            <xmin>1459</xmin>
            <ymin>2565</ymin>
            <xmax>1613</xmax>
            <ymax>2716</ymax>
        </bndbox>
    </object>
    <object>
        <name>詔</name>
        <pose>Unspecified</pose>
        <truncated>0</truncated>
        <difficult>0</difficult>
        <bndbox>
            <xmin>1445</xmin>
            <ymin>2723</ymin>
            <xmax>1597</xmax>
            <ymax>2868</ymax>
        </bndbox>
    </object>
    <object>
        <name>曰</name>
        <pose>Unspecified</pose>
        <truncated>0</truncated>
        <difficult>0</difficult>
        <bndbox>
            <xmin>1463</xmin>
            <ymin>2884</ymin>
            <xmax>1602</xmax>
            <ymax>2992</ymax>
        </bndbox>
    </object>
    <object>
        <name>陵</name>
        <pose>Unspecified</pose>
        <truncated>0</truncated>
        <difficult>0</difficult>
        <bndbox>
            <xmin>1460</xmin>
            <ymin>3005</ymin>
            <xmax>1608</xmax>
            <ymax>3156</ymax>
        </bndbox>
    </object>
    <object>
        <name>寝</name>
        <pose>Unspecified</pose>
        <truncated>0</truncated>
        <difficult>0</difficult>
        <bndbox>
            <xmin>1448</xmin>
            <ymin>3158</ymin>
            <xmax>1594</xmax>
            <ymax>3312</ymax>
        </bndbox>
    </object>
    <object>
        <name>重</name>
        <pose>Unspecified</pose>
        <truncated>0</truncated>
        <difficult>0</difficult>
        <bndbox>
            <xmin>1455</xmin>
            <ymin>3312</ymin>
            <xmax>1592</xmax>
            <ymax>3445</ymax>
        </bndbox>
    </object>
    <object>
        <name>事</name>
        <pose>Unspecified</pose>
        <truncated>0</truncated>
        <difficult>0</difficult>
        <bndbox>
            <xmin>1457</xmin>
            <ymin>3442</ymin>
            <xmax>1602</xmax>
            <ymax>3582</ymax>
        </bndbox>
    </object>
    <object>
        <name>今</name>
        <pose>Unspecified</pose>
        <truncated>0</truncated>
        <difficult>0</difficult>
        <bndbox>
            <xmin>1449</xmin>
            <ymin>3585</ymin>
            <xmax>1617</xmax>
            <ymax>3735</ymax>
        </bndbox>
    </object>
    <object>
        <name>守</name>
        <pose>Unspecified</pose>
        <truncated>0</truncated>
        <difficult>0</difficult>
        <bndbox>
            <xmin>1284</xmin>
            <ymin>816</ymin>
            <xmax>1439</xmax>
            <ymax>960</ymax>
        </bndbox>
    </object>
    <object>
        <name>吏</name>
        <pose>Unspecified</pose>
        <truncated>0</truncated>
        <difficult>0</difficult>
        <bndbox>
            <xmin>1298</xmin>
            <ymin>964</ymin>
            <xmax>1446</xmax>
            <ymax>1103</ymax>
        </bndbox>
    </object>
    <object>
        <name>不</name>
        <pose>Unspecified</pose>
        <truncated>0</truncated>
        <difficult>0</difficult>
        <bndbox>
            <xmin>1290</xmin>
            <ymin>1116</ymin>
            <xmax>1439</xmax>
            <ymax>1241</ymax>
        </bndbox>
    </object>
    <object>
        <name>法</name>
        <pose>Unspecified</pose>
        <truncated>0</truncated>
        <difficult>0</difficult>
        <bndbox>
            <xmin>1289</xmin>
            <ymin>1246</ymin>
            <xmax>1441</xmax>
            <ymax>1385</ymax>
        </bndbox>
    </object>
    <object>
        <name>如</name>
        <pose>Unspecified</pose>
        <truncated>0</truncated>
        <difficult>0</difficult>
        <bndbox>
            <xmin>1271</xmin>
            <ymin>1404</ymin>
            <xmax>1426</xmax>
            <ymax>1529</ymax>
        </bndbox>
    </object>
    <object>
        <name>此</name>
        <pose>Unspecified</pose>
        <truncated>0</truncated>
        <difficult>0</difficult>
        <bndbox>
            <xmin>1275</xmin>
            <ymin>1538</ymin>
            <xmax>1441</xmax>
            <ymax>1659</ymax>
        </bndbox>
    </object>
    <object>
        <name>不</name>
        <pose>Unspecified</pose>
        <truncated>0</truncated>
        <difficult>0</difficult>
        <bndbox>
            <xmin>1272</xmin>
            <ymin>1709</ymin>
            <xmax>1426</xmax>
            <ymax>1846</ymax>
        </bndbox>
    </object>
    <object>
        <name>可</name>
        <pose>Unspecified</pose>
        <truncated>0</truncated>
        <difficult>0</difficult>
        <bndbox>
            <xmin>1280</xmin>
            <ymin>1858</ymin>
            <xmax>1420</xmax>
            <ymax>1998</ymax>
        </bndbox>
    </object>
    <object>
        <name>不</name>
        <pose>Unspecified</pose>
        <truncated>0</truncated>
        <difficult>0</difficult>
        <bndbox>
            <xmin>1280</xmin>
            <ymin>2011</ymin>
            <xmax>1424</xmax>
            <ymax>2141</ymax>
        </bndbox>
    </object>
    <object>
        <name>深</name>
        <pose>Unspecified</pose>
        <truncated>0</truncated>
        <difficult>0</difficult>
        <bndbox>
            <xmin>1264</xmin>
            <ymin>2149</ymin>
            <xmax>1424</xmax>
            <ymax>2294</ymax>
        </bndbox>
    </object>
    <object>
        <name>加</name>
        <pose>Unspecified</pose>
        <truncated>0</truncated>
        <difficult>0</difficult>
        <bndbox>
            <xmin>1256</xmin>
            <ymin>2297</ymin>
            <xmax>1424</xmax>
            <ymax>2409</ymax>
        </bndbox>
    </object>
    <object>
        <name>懲</name>
        <pose>Unspecified</pose>
        <truncated>0</truncated>
        <difficult>0</difficult>
        <bndbox>
            <xmin>1260</xmin>
            <ymin>2421</ymin>
            <xmax>1422</xmax>
            <ymax>2577</ymax>
        </bndbox>
    </object>
    <object>
        <name>治</name>
        <pose>Unspecified</pose>
        <truncated>0</truncated>
        <difficult>0</difficult>
        <bndbox>
            <xmin>1250</xmin>
            <ymin>2576</ymin>
            <xmax>1409</xmax>
            <ymax>2714</ymax>
        </bndbox>
    </object>
    <object>
        <name>其</name>
        <pose>Unspecified</pose>
        <truncated>0</truncated>
        <difficult>0</difficult>
        <bndbox>
            <xmin>1249</xmin>
            <ymin>2715</ymin>
            <xmax>1413</xmax>
            <ymax>2874</ymax>
        </bndbox>
    </object>
    <object>
        <name>選</name>
        <pose>Unspecified</pose>
        <truncated>0</truncated>
        <difficult>0</difficult>
        <bndbox>
            <xmin>1244</xmin>
            <ymin>2877</ymin>
            <xmax>1407</xmax>
            <ymax>3021</ymax>
        </bndbox>
    </object>
    <object>
        <name>强</name>
        <pose>Unspecified</pose>
        <truncated>0</truncated>
        <difficult>0</difficult>
        <bndbox>
            <xmin>1257</xmin>
            <ymin>3025</ymin>
            <xmax>1404</xmax>
            <ymax>3157</ymax>
        </bndbox>
    </object>
    <object>
        <name>毅</name>
        <pose>Unspecified</pose>
        <truncated>0</truncated>
        <difficult>0</difficult>
        <bndbox>
            <xmin>1252</xmin>
            <ymin>3157</ymin>
            <xmax>1406</xmax>
            <ymax>3301</ymax>
        </bndbox>
    </object>
    <object>
        <name>官</name>
        <pose>Unspecified</pose>
        <truncated>0</truncated>
        <difficult>0</difficult>
        <bndbox>
            <xmin>1261</xmin>
            <ymin>3301</ymin>
            <xmax>1397</xmax>
            <ymax>3440</ymax>
        </bndbox>
    </object>
    <object>
        <name>劾</name>
        <pose>Unspecified</pose>
        <truncated>0</truncated>
        <difficult>0</difficult>
        <bndbox>
            <xmin>1252</xmin>
            <ymin>3449</ymin>
            <xmax>1406</xmax>
            <ymax>3590</ymax>
        </bndbox>
    </object>
    <object>
        <name>治</name>
        <pose>Unspecified</pose>
        <truncated>0</truncated>
        <difficult>0</difficult>
        <bndbox>
            <xmin>1259</xmin>
            <ymin>3591</ymin>
            <xmax>1397</xmax>
            <ymax>3729</ymax>
        </bndbox>
    </object>
    <object>
        <name>以</name>
        <pose>Unspecified</pose>
        <truncated>0</truncated>
        <difficult>0</difficult>
        <bndbox>
            <xmin>1092</xmin>
            <ymin>818</ymin>
            <xmax>1245</xmax>
            <ymax>935</ymax>
        </bndbox>
    </object>
    <object>
        <name>聞</name>
        <pose>Unspecified</pose>
        <truncated>0</truncated>
        <difficult>0</difficult>
        <bndbox>
            <xmin>1095</xmin>
            <ymin>952</ymin>
            <xmax>1249</xmax>
            <ymax>1121</ymax>
        </bndbox>
    </object>
    <object>
        <name>初</name>
        <pose>Unspecified</pose>
        <truncated>0</truncated>
        <difficult>0</difficult>
        <bndbox>
            <xmin>1086</xmin>
            <ymin>1123</ymin>
            <xmax>1240</xmax>
            <ymax>1248</ymax>
        </bndbox>
    </object>
    <object>
        <name>永</name>
        <pose>Unspecified</pose>
        <truncated>0</truncated>
        <difficult>0</difficult>
        <bndbox>
            <xmin>1077</xmin>
            <ymin>1397</ymin>
            <xmax>1248</xmax>
            <ymax>1541</ymax>
        </bndbox>
    </object>
    <object>
        <name>熙</name>
        <pose>Unspecified</pose>
        <truncated>0</truncated>
        <difficult>0</difficult>
        <bndbox>
            <xmin>1084</xmin>
            <ymin>1544</ymin>
            <xmax>1243</xmax>
            <ymax>1679</ymax>
        </bndbox>
    </object>
    <object>
        <name>陵</name>
        <pose>Unspecified</pose>
        <truncated>0</truncated>
        <difficult>0</difficult>
        <bndbox>
            <xmin>1082</xmin>
            <ymin>1685</ymin>
            <xmax>1234</xmax>
            <ymax>1848</ymax>
        </bndbox>
    </object>
    <object>
        <name>之</name>
        <pose>Unspecified</pose>
        <truncated>0</truncated>
        <difficult>0</difficult>
        <bndbox>
            <xmin>1082</xmin>
            <ymin>1854</ymin>
            <xmax>1231</xmax>
            <ymax>1976</ymax>
        </bndbox>
    </object>
    <object>
        <name>艮</name>
        <pose>Unspecified</pose>
        <truncated>0</truncated>
        <difficult>0</difficult>
        <bndbox>
            <xmin>1082</xmin>
            <ymin>1990</ymin>
            <xmax>1230</xmax>
            <ymax>2131</ymax>
        </bndbox>
    </object>
    <object>
        <name>巽</name>
        <pose>Unspecified</pose>
        <truncated>0</truncated>
        <difficult>0</difficult>
        <bndbox>
            <xmin>1069</xmin>
            <ymin>2138</ymin>
            <xmax>1230</xmax>
            <ymax>2295</ymax>
        </bndbox>
    </object>
    <object>
        <name>方</name>
        <pose>Unspecified</pose>
        <truncated>0</truncated>
        <difficult>0</difficult>
        <bndbox>
            <xmin>1074</xmin>
            <ymin>2294</ymin>
            <xmax>1224</xmax>
            <ymax>2423</ymax>
        </bndbox>
    </object>
    <object>
        <name>築</name>
        <pose>Unspecified</pose>
        <truncated>0</truncated>
        <difficult>0</difficult>
        <bndbox>
            <xmin>1073</xmin>
            <ymin>2426</ymin>
            <xmax>1219</xmax>
            <ymax>2579</ymax>
        </bndbox>
    </object>
    <object>
        <name>隄</name>
        <pose>Unspecified</pose>
        <truncated>0</truncated>
        <difficult>0</difficult>
        <bndbox>
            <xmin>1073</xmin>
            <ymin>2577</ymin>
            <xmax>1227</xmax>
            <ymax>2716</ymax>
        </bndbox>
    </object>
    <object>
        <name>以</name>
        <pose>Unspecified</pose>
        <truncated>0</truncated>
        <difficult>0</difficult>
        <bndbox>
            <xmin>1078</xmin>
            <ymin>2733</ymin>
            <xmax>1213</xmax>
            <ymax>2847</ymax>
        </bndbox>
    </object>
    <object>
        <name>鎮</name>
        <pose>Unspecified</pose>
        <truncated>0</truncated>
        <difficult>0</difficult>
        <bndbox>
            <xmin>1060</xmin>
            <ymin>2859</ymin>
            <xmax>1228</xmax>
            <ymax>3018</ymax>
        </bndbox>
    </object>
    <object>
        <name>土</name>
        <pose>Unspecified</pose>
        <truncated>0</truncated>
        <difficult>0</difficult>
        <bndbox>
            <xmin>1071</xmin>
            <ymin>3023</ymin>
            <xmax>1226</xmax>
            <ymax>3154</ymax>
        </bndbox>
    </object>
    <object>
        <name>至</name>
        <pose>Unspecified</pose>
        <truncated>0</truncated>
        <difficult>0</difficult>
        <bndbox>
            <xmin>1071</xmin>
            <ymin>3167</ymin>
            <xmax>1218</xmax>
            <ymax>3296</ymax>
        </bndbox>
    </object>
    <object>
        <name>是</name>
        <pose>Unspecified</pose>
        <truncated>0</truncated>
        <difficult>0</difficult>
        <bndbox>
            <xmin>1066</xmin>
            <ymin>3300</ymin>
            <xmax>1224</xmax>
            <ymax>3441</ymax>
        </bndbox>
    </object>
    <object>
        <name>因</name>
        <pose>Unspecified</pose>
        <truncated>0</truncated>
        <difficult>0</difficult>
        <bndbox>
            <xmin>1082</xmin>
            <ymin>3447</ymin>
            <xmax>1201</xmax>
            <ymax>3576</ymax>
        </bndbox>
    </object>
    <object>
        <name>日</name>
        <pose>Unspecified</pose>
        <truncated>0</truncated>
        <difficult>0</difficult>
        <bndbox>
            <xmin>1089</xmin>
            <ymin>3594</ymin>
            <xmax>1181</xmax>
            <ymax>3722</ymax>
        </bndbox>
    </object>
    <object>
        <name>官</name>
        <pose>Unspecified</pose>
        <truncated>0</truncated>
        <difficult>0</difficult>
        <bndbox>
            <xmin>909</xmin>
            <ymin>814</ymin>
            <xmax>1050</xmax>
            <ymax>957</ymax>
        </bndbox>
    </object>
    <object>
        <name>有</name>
        <pose>Unspecified</pose>
        <truncated>0</truncated>
        <difficult>0</difficult>
        <bndbox>
            <xmin>903</xmin>
            <ymin>963</ymin>
            <xmax>1044</xmax>
            <ymax>1107</ymax>
        </bndbox>
    </object>
    <object>
        <name>請</name>
        <pose>Unspecified</pose>
        <truncated>0</truncated>
        <difficult>0</difficult>
        <bndbox>
            <xmin>903</xmin>
            <ymin>1110</ymin>
            <xmax>1049</xmax>
            <ymax>1250</ymax>
        </bndbox>
    </object>
    <object>
        <name>乃</name>
        <pose>Unspecified</pose>
        <truncated>0</truncated>
        <difficult>0</difficult>
        <bndbox>
            <xmin>899</xmin>
            <ymin>1252</ymin>
            <xmax>1029</xmax>
            <ymax>1402</ymax>
        </bndbox>
    </object>
    <object>
        <name>命</name>
        <pose>Unspecified</pose>
        <truncated>0</truncated>
        <difficult>0</difficult>
        <bndbox>
            <xmin>900</xmin>
            <ymin>1413</ymin>
            <xmax>1045</xmax>
            <ymax>1531</ymax>
        </bndbox>
    </object>
    <object>
        <name>為</name>
        <pose>Unspecified</pose>
        <truncated>0</truncated>
        <difficult>0</difficult>
        <bndbox>
            <xmin>904</xmin>
            <ymin>1544</ymin>
            <xmax>1038</xmax>
            <ymax>1695</ymax>
        </bndbox>
    </object>
    <object>
        <name>隄</name>
        <pose>Unspecified</pose>
        <truncated>0</truncated>
        <difficult>0</difficult>
        <bndbox>
            <xmin>890</xmin>
            <ymin>1700</ymin>
            <xmax>1049</xmax>
            <ymax>1838</ymax>
        </bndbox>
    </object>
    <object>
        <name>扵</name>
        <pose>Unspecified</pose>
        <truncated>0</truncated>
        <difficult>0</difficult>
        <bndbox>
            <xmin>886</xmin>
            <ymin>1839</ymin>
            <xmax>1033</xmax>
            <ymax>1985</ymax>
        </bndbox>
    </object>
    <object>
        <name>永</name>
        <pose>Unspecified</pose>
        <truncated>0</truncated>
        <difficult>0</difficult>
        <bndbox>
            <xmin>884</xmin>
            <ymin>2126</ymin>
            <xmax>1044</xmax>
            <ymax>2279</ymax>
        </bndbox>
    </object>
    <object>
        <name>厚</name>
        <pose>Unspecified</pose>
        <truncated>0</truncated>
        <difficult>0</difficult>
        <bndbox>
            <xmin>880</xmin>
            <ymin>2276</ymin>
            <xmax>1037</xmax>
            <ymax>2428</ymax>
        </bndbox>
    </object>
    <object>
        <name>陵</name>
        <pose>Unspecified</pose>
        <truncated>0</truncated>
        <difficult>0</difficult>
        <bndbox>
            <xmin>874</xmin>
            <ymin>2426</ymin>
            <xmax>1042</xmax>
            <ymax>2578</ymax>
        </bndbox>
    </object>
    <object>
        <name>及</name>
        <pose>Unspecified</pose>
        <truncated>0</truncated>
        <difficult>0</difficult>
        <bndbox>
            <xmin>883</xmin>
            <ymin>2575</ymin>
            <xmax>1046</xmax>
            <ymax>2701</ymax>
        </bndbox>
    </object>
    <object>
        <name>濮</name>
        <pose>Unspecified</pose>
        <truncated>0</truncated>
        <difficult>0</difficult>
        <bndbox>
            <xmin>886</xmin>
            <ymin>2708</ymin>
            <xmax>1041</xmax>
            <ymax>2862</ymax>
        </bndbox>
    </object>
    <object>
        <name>園</name>
        <pose>Unspecified</pose>
        <truncated>0</truncated>
        <difficult>0</difficult>
        <bndbox>
            <xmin>893</xmin>
            <ymin>2869</ymin>
            <xmax>1027</xmax>
            <ymax>3011</ymax>
        </bndbox>
    </object>
    <object>
        <name>之</name>
        <pose>Unspecified</pose>
        <truncated>0</truncated>
        <difficult>0</difficult>
        <bndbox>
            <xmin>869</xmin>
            <ymin>3022</ymin>
            <xmax>1038</xmax>
            <ymax>3138</ymax>
        </bndbox>
    </object>
    <object>
        <name>東</name>
        <pose>Unspecified</pose>
        <truncated>0</truncated>
        <difficult>0</difficult>
        <bndbox>
            <xmin>873</xmin>
            <ymin>3148</ymin>
            <xmax>1042</xmax>
            <ymax>3301</ymax>
        </bndbox>
    </object>
    <object>
        <name>行</name>
        <pose>Unspecified</pose>
        <truncated>0</truncated>
        <difficult>0</difficult>
        <bndbox>
            <xmin>874</xmin>
            <ymin>3303</ymin>
            <xmax>1039</xmax>
            <ymax>3440</ymax>
        </bndbox>
    </object>
    <object>
        <name>鎮</name>
        <pose>Unspecified</pose>
        <truncated>0</truncated>
        <difficult>0</difficult>
        <bndbox>
            <xmin>866</xmin>
            <ymin>3439</ymin>
            <xmax>1044</xmax>
            <ymax>3589</ymax>
        </bndbox>
    </object>
    <object>
        <name>土</name>
        <pose>Unspecified</pose>
        <truncated>0</truncated>
        <difficult>0</difficult>
        <bndbox>
            <xmin>874</xmin>
            <ymin>3596</ymin>
            <xmax>1036</xmax>
            <ymax>3712</ymax>
        </bndbox>
    </object>
    <object>
        <name>法</name>
        <pose>Unspecified</pose>
        <truncated>0</truncated>
        <difficult>0</difficult>
        <bndbox>
            <xmin>710</xmin>
            <ymin>807</ymin>
            <xmax>875</xmax>
            <ymax>950</ymax>
        </bndbox>
    </object>
    <object>
        <name>各</name>
        <pose>Unspecified</pose>
        <truncated>0</truncated>
        <difficult>0</difficult>
        <bndbox>
            <xmin>709</xmin>
            <ymin>963</ymin>
            <xmax>864</xmax>
            <ymax>1093</ymax>
        </bndbox>
    </object>
    <object>
        <name>扵</name>
        <pose>Unspecified</pose>
        <truncated>0</truncated>
        <difficult>0</difficult>
        <bndbox>
            <xmin>705</xmin>
            <ymin>1097</ymin>
            <xmax>851</xmax>
            <ymax>1233</ymax>
        </bndbox>
    </object>
    <object>
        <name>其</name>
        <pose>Unspecified</pose>
        <truncated>0</truncated>
        <difficult>0</difficult>
        <bndbox>
            <xmin>700</xmin>
            <ymin>1236</ymin>
            <xmax>860</xmax>
            <ymax>1388</ymax>
        </bndbox>
    </object>
    <object>
        <name>方</name>
        <pose>Unspecified</pose>
        <truncated>0</truncated>
        <difficult>0</difficult>
        <bndbox>
            <xmin>695</xmin>
            <ymin>1394</ymin>
            <xmax>856</xmax>
            <ymax>1542</ymax>
        </bndbox>
    </object>
    <object>
        <name>以</name>
        <pose>Unspecified</pose>
        <truncated>0</truncated>
        <difficult>0</difficult>
        <bndbox>
            <xmin>696</xmin>
            <ymin>1548</ymin>
            <xmax>854</xmax>
            <ymax>1665</ymax>
        </bndbox>
    </object>
    <object>
        <name>珎</name>
        <pose>Unspecified</pose>
        <truncated>0</truncated>
        <difficult>0</difficult>
        <bndbox>
            <xmin>704</xmin>
            <ymin>1691</ymin>
            <xmax>852</xmax>
            <ymax>1826</ymax>
        </bndbox>
    </object>
    <object>
        <name>寳</name>
        <pose>Unspecified</pose>
        <truncated>0</truncated>
        <difficult>0</difficult>
        <bndbox>
            <xmin>703</xmin>
            <ymin>1829</ymin>
            <xmax>849</xmax>
            <ymax>1995</ymax>
        </bndbox>
    </object>
    <object>
        <name>玉</name>
        <pose>Unspecified</pose>
        <truncated>0</truncated>
        <difficult>0</difficult>
        <bndbox>
            <xmin>696</xmin>
            <ymin>2003</ymin>
            <xmax>849</xmax>
            <ymax>2120</ymax>
        </bndbox>
    </object>
    <object>
        <name>石</name>
        <pose>Unspecified</pose>
        <truncated>0</truncated>
        <difficult>0</difficult>
        <bndbox>
            <xmin>707</xmin>
            <ymin>2145</ymin>
            <xmax>832</xmax>
            <ymax>2274</ymax>
        </bndbox>
    </object>
    <object>
        <name>為</name>
        <pose>Unspecified</pose>
        <truncated>0</truncated>
        <difficult>0</difficult>
        <bndbox>
            <xmin>704</xmin>
            <ymin>2283</ymin>
            <xmax>849</xmax>
            <ymax>2423</ymax>
        </bndbox>
    </object>
    <object>
        <name>獸</name>
        <pose>Unspecified</pose>
        <truncated>0</truncated>
        <difficult>0</difficult>
        <bndbox>
            <xmin>703</xmin>
            <ymin>2426</ymin>
            <xmax>848</xmax>
            <ymax>2565</ymax>
        </bndbox>
    </object>
    <object>
        <name>瘗</name>
        <pose>Unspecified</pose>
        <truncated>0</truncated>
        <difficult>0</difficult>
        <bndbox>
            <xmin>692</xmin>
            <ymin>2565</ymin>
            <xmax>857</xmax>
            <ymax>2715</ymax>
        </bndbox>
    </object>
    <object>
        <name>之</name>
        <pose>Unspecified</pose>
        <truncated>0</truncated>
        <difficult>0</difficult>
        <bndbox>
            <xmin>695</xmin>
            <ymin>2720</ymin>
            <xmax>856</xmax>
            <ymax>2850</ymax>
        </bndbox>
    </object>
    <object>
        <name>詔</name>
        <pose>Unspecified</pose>
        <truncated>0</truncated>
        <difficult>0</difficult>
        <bndbox>
            <xmin>696</xmin>
            <ymin>2866</ymin>
            <xmax>829</xmax>
            <ymax>2994</ymax>
        </bndbox>
    </object>
    <object>
        <name>朝</name>
        <pose>Unspecified</pose>
        <truncated>0</truncated>
        <difficult>0</difficult>
        <bndbox>
            <xmin>696</xmin>
            <ymin>3006</ymin>
            <xmax>833</xmax>
            <ymax>3153</ymax>
        </bndbox>
    </object>
    <object>
        <name>陵</name>
        <pose>Unspecified</pose>
        <truncated>0</truncated>
        <difficult>0</difficult>
        <bndbox>
            <xmin>698</xmin>
            <ymin>3155</ymin>
            <xmax>843</xmax>
            <ymax>3299</ymax>
        </bndbox>
    </object>
    <object>
        <name>官</name>
        <pose>Unspecified</pose>
        <truncated>0</truncated>
        <difficult>0</difficult>
        <bndbox>
            <xmin>693</xmin>
            <ymin>3303</ymin>
            <xmax>846</xmax>
            <ymax>3442</ymax>
        </bndbox>
    </object>
    <object>
        <name>非</name>
        <pose>Unspecified</pose>
        <truncated>0</truncated>
        <difficult>0</difficult>
        <bndbox>
            <xmin>692</xmin>
            <ymin>3443</ymin>
            <xmax>847</xmax>
            <ymax>3585</ymax>
        </bndbox>
    </object>
    <object>
        <name>嘗</name>
        <pose>Unspecified</pose>
        <truncated>0</truncated>
        <difficult>0</difficult>
        <bndbox>
            <xmin>695</xmin>
            <ymin>3589</ymin>
            <xmax>848</xmax>
            <ymax>3738</ymax>
        </bndbox>
    </object>
    <object>
        <name>任</name>
        <pose>Unspecified</pose>
        <truncated>0</truncated>
        <difficult>0</difficult>
        <bndbox>
            <xmin>521</xmin>
            <ymin>820</ymin>
            <xmax>669</xmax>
            <ymax>935</ymax>
        </bndbox>
    </object>
    <object>
        <name>執</name>
        <pose>Unspecified</pose>
        <truncated>0</truncated>
        <difficult>0</difficult>
        <bndbox>
            <xmin>515</xmin>
            <ymin>942</ymin>
            <xmax>664</xmax>
            <ymax>1079</ymax>
        </bndbox>
    </object>
    <object>
        <name>政</name>
        <pose>Unspecified</pose>
        <truncated>0</truncated>
        <difficult>0</difficult>
        <bndbox>
            <xmin>505</xmin>
            <ymin>1092</ymin>
            <xmax>687</xmax>
            <ymax>1229</ymax>
        </bndbox>
    </object>
    <object>
        <name>事</name>
        <pose>Unspecified</pose>
        <truncated>0</truncated>
        <difficult>0</difficult>
        <bndbox>
            <xmin>517</xmin>
            <ymin>1233</ymin>
            <xmax>670</xmax>
            <ymax>1394</ymax>
        </bndbox>
    </object>
    <object>
        <name>止</name>
        <pose>Unspecified</pose>
        <truncated>0</truncated>
        <difficult>0</difficult>
        <bndbox>
            <xmin>498</xmin>
            <ymin>1398</ymin>
            <xmax>668</xmax>
            <ymax>1512</ymax>
        </bndbox>
    </object>
    <object>
        <name>奠</name>
        <pose>Unspecified</pose>
        <truncated>0</truncated>
        <difficult>0</difficult>
        <bndbox>
            <xmin>501</xmin>
            <ymin>1523</ymin>
            <xmax>671</xmax>
            <ymax>1685</ymax>
        </bndbox>
    </object>
    <object>
        <name>獻</name>
        <pose>Unspecified</pose>
        <truncated>0</truncated>
        <difficult>0</difficult>
        <bndbox>
            <xmin>500</xmin>
            <ymin>1687</ymin>
            <xmax>661</xmax>
            <ymax>1832</ymax>
        </bndbox>
    </object>
    <object>
        <name>薦</name>
        <pose>Unspecified</pose>
        <truncated>0</truncated>
        <difficult>0</difficult>
        <bndbox>
            <xmin>501</xmin>
            <ymin>1831</ymin>
            <xmax>654</xmax>
            <ymax>1982</ymax>
        </bndbox>
    </object>
    <object>
        <name>新</name>
        <pose>Unspecified</pose>
        <truncated>0</truncated>
        <difficult>0</difficult>
        <bndbox>
            <xmin>504</xmin>
            <ymin>1980</ymin>
            <xmax>664</xmax>
            <ymax>2125</ymax>
        </bndbox>
    </object>
    <object>
        <name>其</name>
        <pose>Unspecified</pose>
        <truncated>0</truncated>
        <difficult>0</difficult>
        <bndbox>
            <xmin>505</xmin>
            <ymin>2127</ymin>
            <xmax>661</xmax>
            <ymax>2278</ymax>
        </bndbox>
    </object>
    <object>
        <name>勿</name>
        <pose>Unspecified</pose>
        <truncated>0</truncated>
        <difficult>0</difficult>
        <bndbox>
            <xmin>508</xmin>
            <ymin>2283</ymin>
            <xmax>647</xmax>
            <ymax>2413</ymax>
        </bndbox>
    </object>
    <object>
        <name>進</name>
        <pose>Unspecified</pose>
        <truncated>0</truncated>
        <difficult>0</difficult>
        <bndbox>
            <xmin>500</xmin>
            <ymin>2421</ymin>
            <xmax>649</xmax>
            <ymax>2565</ymax>
        </bndbox>
    </object>
    <object>
        <name>湯</name>
        <pose>Unspecified</pose>
        <truncated>0</truncated>
        <difficult>0</difficult>
        <bndbox>
            <xmin>506</xmin>
            <ymin>2566</ymin>
            <xmax>659</xmax>
            <ymax>2717</ymax>
        </bndbox>
    </object>
    <object>
        <name>特</name>
        <pose>Unspecified</pose>
        <truncated>0</truncated>
        <difficult>0</difficult>
        <bndbox>
            <xmin>504</xmin>
            <ymin>2712</ymin>
            <xmax>666</xmax>
            <ymax>2859</ymax>
        </bndbox>
    </object>
    <object>
        <name>拜</name>
        <pose>Unspecified</pose>
        <truncated>0</truncated>
        <difficult>0</difficult>
        <bndbox>
            <xmin>500</xmin>
            <ymin>2863</ymin>
            <xmax>667</xmax>
            <ymax>3009</ymax>
        </bndbox>
    </object>
    <object>
        <name>應</name>
        <pose>Unspecified</pose>
        <truncated>0</truncated>
        <difficult>0</difficult>
        <bndbox>
            <xmin>500</xmin>
            <ymin>3015</ymin>
            <xmax>667</xmax>
            <ymax>3158</ymax>
        </bndbox>
    </object>
    <object>
        <name>諸</name>
        <pose>Unspecified</pose>
        <truncated>0</truncated>
        <difficult>0</difficult>
        <bndbox>
            <xmin>505</xmin>
            <ymin>3155</ymin>
            <xmax>664</xmax>
            <ymax>3295</ymax>
        </bndbox>
    </object>
    <object>
        <name>陵</name>
        <pose>Unspecified</pose>
        <truncated>0</truncated>
        <difficult>0</difficult>
        <bndbox>
            <xmin>506</xmin>
            <ymin>3297</ymin>
            <xmax>664</xmax>
            <ymax>3437</ymax>
        </bndbox>
    </object>
    <object>
        <name>官</name>
        <pose>Unspecified</pose>
        <truncated>0</truncated>
        <difficult>0</difficult>
        <bndbox>
            <xmin>503</xmin>
            <ymin>3439</ymin>
            <xmax>657</xmax>
            <ymax>3582</ymax>
        </bndbox>
    </object>
    <object>
        <name>物</name>
        <pose>Unspecified</pose>
        <truncated>0</truncated>
        <difficult>0</difficult>
        <bndbox>
            <xmin>502</xmin>
            <ymin>3588</ymin>
            <xmax>666</xmax>
            <ymax>3726</ymax>
        </bndbox>
    </object>
    <object>
        <name>皆</name>
        <pose>Unspecified</pose>
        <truncated>0</truncated>
        <difficult>0</difficult>
        <bndbox>
            <xmin>311</xmin>
            <ymin>806</ymin>
            <xmax>463</xmax>
            <ymax>957</ymax>
        </bndbox>
    </object>
    <object>
        <name>籍</name>
        <pose>Unspecified</pose>
        <truncated>0</truncated>
        <difficult>0</difficult>
        <bndbox>
            <xmin>307</xmin>
            <ymin>959</ymin>
            <xmax>464</xmax>
            <ymax>1112</ymax>
        </bndbox>
    </object>
    <object>
        <name>二</name>
        <pose>Unspecified</pose>
        <truncated>0</truncated>
        <difficult>0</difficult>
        <bndbox>
            <xmin>305</xmin>
            <ymin>1119</ymin>
            <xmax>461</xmax>
            <ymax>1212</ymax>
        </bndbox>
    </object>
    <object>
        <name>年</name>
        <pose>Unspecified</pose>
        <truncated>0</truncated>
        <difficult>0</difficult>
        <bndbox>
            <xmin>306</xmin>
            <ymin>1238</ymin>
            <xmax>455</xmax>
            <ymax>1408</ymax>
        </bndbox>
    </object>
    <object>
        <name>一</name>
        <pose>Unspecified</pose>
        <truncated>0</truncated>
        <difficult>0</difficult>
        <bndbox>
            <xmin>297</xmin>
            <ymin>1427</ymin>
            <xmax>462</xmax>
            <ymax>1481</ymax>
        </bndbox>
    </object>
    <object>
        <name>遣</name>
        <pose>Unspecified</pose>
        <truncated>0</truncated>
        <difficult>0</difficult>
        <bndbox>
            <xmin>284</xmin>
            <ymin>1513</ymin>
            <xmax>463</xmax>
            <ymax>1688</ymax>
        </bndbox>
    </object>
    <object>
        <name>官</name>
        <pose>Unspecified</pose>
        <truncated>0</truncated>
        <difficult>0</difficult>
        <bndbox>
            <xmin>292</xmin>
            <ymin>1689</ymin>
            <xmax>455</xmax>
            <ymax>1844</ymax>
        </bndbox>
    </object>
    <object>
        <name>檢</name>
        <pose>Unspecified</pose>
        <truncated>0</truncated>
        <difficult>0</difficult>
        <bndbox>
            <xmin>295</xmin>
            <ymin>1842</ymin>
            <xmax>467</xmax>
            <ymax>1975</ymax>
        </bndbox>
    </object>
    <object>
        <name>察</name>
        <pose>Unspecified</pose>
        <truncated>0</truncated>
        <difficult>0</difficult>
        <bndbox>
            <xmin>291</xmin>
            <ymin>1973</ymin>
            <xmax>466</xmax>
            <ymax>2129</ymax>
        </bndbox>
    </object>
    <object>
        <name>陵</name>
        <pose>Unspecified</pose>
        <truncated>0</truncated>
        <difficult>0</difficult>
        <bndbox>
            <xmin>292</xmin>
            <ymin>2127</ymin>
            <xmax>461</xmax>
            <ymax>2271</ymax>
        </bndbox>
    </object>
    <object>
        <name>臺</name>
        <pose>Unspecified</pose>
        <truncated>0</truncated>
        <difficult>0</difficult>
        <bndbox>
            <xmin>293</xmin>
            <ymin>2269</ymin>
            <xmax>456</xmax>
            <ymax>2422</ymax>
        </bndbox>
    </object>
    <object>
        <name>令</name>
        <pose>Unspecified</pose>
        <truncated>0</truncated>
        <difficult>0</difficult>
        <bndbox>
            <xmin>285</xmin>
            <ymin>2423</ymin>
            <xmax>466</xmax>
            <ymax>2555</ymax>
        </bndbox>
    </object>
    <object>
        <name>通</name>
        <pose>Unspecified</pose>
        <truncated>0</truncated>
        <difficult>0</difficult>
        <bndbox>
            <xmin>288</xmin>
            <ymin>2562</ymin>
            <xmax>445</xmax>
            <ymax>2708</ymax>
        </bndbox>
    </object>
    <object>
        <name>治</name>
        <pose>Unspecified</pose>
        <truncated>0</truncated>
        <difficult>0</difficult>
        <bndbox>
            <xmin>289</xmin>
            <ymin>2708</ymin>
            <xmax>439</xmax>
            <ymax>2848</ymax>
        </bndbox>
    </object>
    <object>
        <name>陵</name>
        <pose>Unspecified</pose>
        <truncated>0</truncated>
        <difficult>0</difficult>
        <bndbox>
            <xmin>290</xmin>
            <ymin>2852</ymin>
            <xmax>443</xmax>
            <ymax>3001</ymax>
        </bndbox>
    </object>
    <object>
        <name>事</name>
        <pose>Unspecified</pose>
        <truncated>0</truncated>
        <difficult>0</difficult>
        <bndbox>
            <xmin>297</xmin>
            <ymin>3002</ymin>
            <xmax>449</xmax>
            <ymax>3158</ymax>
        </bndbox>
    </object>
    <object>
        <name>隸</name>
        <pose>Unspecified</pose>
        <truncated>0</truncated>
        <difficult>0</difficult>
        <bndbox>
            <xmin>279</xmin>
            <ymin>3156</ymin>
            <xmax>453</xmax>
            <ymax>3295</ymax>
        </bndbox>
    </object>
    <object>
        <name>太</name>
        <pose>Unspecified</pose>
        <truncated>0</truncated>
        <difficult>0</difficult>
        <bndbox>
            <xmin>287</xmin>
            <ymin>3292</ymin>
            <xmax>449</xmax>
            <ymax>3417</ymax>
        </bndbox>
    </object>
    <object>
        <name>常</name>
        <pose>Unspecified</pose>
        <truncated>0</truncated>
        <difficult>0</difficult>
        <bndbox>
            <xmin>294</xmin>
            <ymin>3419</ymin>
            <xmax>450</xmax>
            <ymax>3572</ymax>
        </bndbox>
    </object>
    <object>
        <name>寺</name>
        <pose>Unspecified</pose>
        <truncated>0</truncated>
        <difficult>0</difficult>
        <bndbox>
            <xmin>294</xmin>
            <ymin>3577</ymin>
            <xmax>452</xmax>
            <ymax>3733</ymax>
        </bndbox>
    </object>
    <object>
        <name>仍</name>
        <pose>Unspecified</pose>
        <truncated>0</truncated>
        <difficult>0</difficult>
        <bndbox>
            <xmin>102</xmin>
            <ymin>815</ymin>
            <xmax>249</xmax>
            <ymax>950</ymax>
        </bndbox>
    </object>
    <object>
        <name>專</name>
        <pose>Unspecified</pose>
        <truncated>0</truncated>
        <difficult>0</difficult>
        <bndbox>
            <xmin>113</xmin>
            <ymin>950</ymin>
            <xmax>252</xmax>
            <ymax>1089</ymax>
        </bndbox>
    </object>
    <object>
        <name>按</name>
        <pose>Unspecified</pose>
        <truncated>0</truncated>
        <difficult>0</difficult>
        <bndbox>
            <xmin>100</xmin>
            <ymin>1090</ymin>
            <xmax>259</xmax>
            <ymax>1232</ymax>
        </bndbox>
    </object>
    <object>
        <name>視</name>
        <pose>Unspecified</pose>
        <truncated>0</truncated>
        <difficult>0</difficult>
        <bndbox>
            <xmin>102</xmin>
            <ymin>1241</ymin>
            <xmax>252</xmax>
            <ymax>1380</ymax>
        </bndbox>
    </object>
    <object>
        <name>陵</name>
        <pose>Unspecified</pose>
        <truncated>0</truncated>
        <difficult>0</difficult>
        <bndbox>
            <xmin>101</xmin>
            <ymin>1385</ymin>
            <xmax>248</xmax>
            <ymax>1518</ymax>
        </bndbox>
    </object>
    <object>
        <name>域</name>
        <pose>Unspecified</pose>
        <truncated>0</truncated>
        <difficult>0</difficult>
        <bndbox>
            <xmin>97</xmin>
            <ymin>1524</ymin>
            <xmax>254</xmax>
            <ymax>1662</ymax>
        </bndbox>
    </object>
    <object>
        <name>或</name>
        <pose>Unspecified</pose>
        <truncated>0</truncated>
        <difficult>0</difficult>
        <bndbox>
            <xmin>103</xmin>
            <ymin>1668</ymin>
            <xmax>258</xmax>
            <ymax>1825</ymax>
        </bndbox>
    </object>
    <object>
        <name>内</name>
        <pose>Unspecified</pose>
        <truncated>0</truncated>
        <difficult>0</difficult>
        <bndbox>
            <xmin>114</xmin>
            <ymin>1836</ymin>
            <xmax>243</xmax>
            <ymax>1963</ymax>
        </bndbox>
    </object>
    <object>
        <name>外</name>
        <pose>Unspecified</pose>
        <truncated>0</truncated>
        <difficult>0</difficult>
        <bndbox>
            <xmin>103</xmin>
            <ymin>1971</ymin>
            <xmax>268</xmax>
            <ymax>2113</ymax>
        </bndbox>
    </object>
    <object>
        <name>林</name>
        <pose>Unspecified</pose>
        <truncated>0</truncated>
        <difficult>0</difficult>
        <bndbox>
            <xmin>96</xmin>
            <ymin>2116</ymin>
            <xmax>265</xmax>
            <ymax>2260</ymax>
        </bndbox>
    </object>
    <object>
        <name>木</name>
        <pose>Unspecified</pose>
        <truncated>0</truncated>
        <difficult>0</difficult>
        <bndbox>
            <xmin>91</xmin>
            <ymin>2260</ymin>
            <xmax>263</xmax>
            <ymax>2410</ymax>
        </bndbox>
    </object>
    <object>
        <name>歳</name>
        <pose>Unspecified</pose>
        <truncated>0</truncated>
        <difficult>0</difficult>
        <bndbox>
            <xmin>89</xmin>
            <ymin>2408</ymin>
            <xmax>253</xmax>
            <ymax>2559</ymax>
        </bndbox>
    </object>
    <object>
        <name>以</name>
        <pose>Unspecified</pose>
        <truncated>0</truncated>
        <difficult>0</difficult>
        <bndbox>
            <xmin>85</xmin>
            <ymin>2568</ymin>
            <xmax>244</xmax>
            <ymax>2685</ymax>
        </bndbox>
    </object>
    <object>
        <name>數</name>
        <pose>Unspecified</pose>
        <truncated>0</truncated>
        <difficult>0</difficult>
        <bndbox>
            <xmin>84</xmin>
            <ymin>2696</ymin>
            <xmax>255</xmax>
            <ymax>2849</ymax>
        </bndbox>
    </object>
    <object>
        <name>申</name>
        <pose>Unspecified</pose>
        <truncated>0</truncated>
        <difficult>0</difficult>
        <bndbox>
            <xmin>109</xmin>
            <ymin>2852</ymin>
            <xmax>236</xmax>
            <ymax>3000</ymax>
        </bndbox>
    </object>
    <object>
        <name>寺</name>
        <pose>Unspecified</pose>
        <truncated>0</truncated>
        <difficult>0</difficult>
        <bndbox>
            <xmin>109</xmin>
            <ymin>3003</ymin>
            <xmax>242</xmax>
            <ymax>3150</ymax>
        </bndbox>
    </object>
    <object>
        <name>其</name>
        <pose>Unspecified</pose>
        <truncated>0</truncated>
        <difficult>0</difficult>
        <bndbox>
            <xmin>93</xmin>
            <ymin>3149</ymin>
            <xmax>236</xmax>
            <ymax>3291</ymax>
        </bndbox>
    </object>
    <object>
        <name>典</name>
        <pose>Unspecified</pose>
        <truncated>0</truncated>
        <difficult>0</difficult>
        <bndbox>
            <xmin>92</xmin>
            <ymin>3289</ymin>
            <xmax>242</xmax>
            <ymax>3415</ymax>
        </bndbox>
    </object>
    <object>
        <name>領</name>
        <pose>Unspecified</pose>
        <truncated>0</truncated>
        <difficult>0</difficult>
        <bndbox>
            <xmin>98</xmin>
            <ymin>3435</ymin>
            <xmax>239</xmax>
            <ymax>3581</ymax>
        </bndbox>
    </object>
    <object>
        <name>官</name>
        <pose>Unspecified</pose>
        <truncated>0</truncated>
        <difficult>0</difficult>
        <bndbox>
            <xmin>99</xmin>
            <ymin>3585</ymin>
            <xmax>254</xmax>
            <ymax>3733</ymax>
        </bndbox>
    </object>
</annotation>
