<?xml version="1.0" ?>
<annotation>
    <filename>文献通考_三百四十八卷_元_马端临撰_明嘉靖三年司礼监刊本_哈佛大学图书馆藏_黑白版_14202.jpg</filename>
    <source/>
    <size>
        <width>2229</width>
        <height>4151</height>
        <depth>3</depth>
    </size>
    <segmented>0</segmented>
    <object>
        <name>王</name>
        <pose>Unspecified</pose>
        <truncated>0</truncated>
        <difficult>0</difficult>
        <bndbox>
            <xmin>1934</xmin>
            <ymin>768</ymin>
            <xmax>2088</xmax>
            <ymax>895</ymax>
        </bndbox>
    </object>
    <object>
        <name>直</name>
        <pose>Unspecified</pose>
        <truncated>0</truncated>
        <difficult>0</difficult>
        <bndbox>
            <xmin>1933</xmin>
            <ymin>898</ymin>
            <xmax>2090</xmax>
            <ymax>1040</ymax>
        </bndbox>
    </object>
    <object>
        <name>講</name>
        <pose>Unspecified</pose>
        <truncated>0</truncated>
        <difficult>0</difficult>
        <bndbox>
            <xmin>1936</xmin>
            <ymin>1048</ymin>
            <xmax>2097</xmax>
            <ymax>1200</ymax>
        </bndbox>
    </object>
    <object>
        <name>集</name>
        <pose>Unspecified</pose>
        <truncated>0</truncated>
        <difficult>0</difficult>
        <bndbox>
            <xmin>1943</xmin>
            <ymin>1202</ymin>
            <xmax>2098</xmax>
            <ymax>1375</ymax>
        </bndbox>
    </object>
    <object>
        <name>十</name>
        <pose>Unspecified</pose>
        <truncated>0</truncated>
        <difficult>0</difficult>
        <bndbox>
            <xmin>1941</xmin>
            <ymin>1377</ymin>
            <xmax>2093</xmax>
            <ymax>1493</ymax>
        </bndbox>
    </object>
    <object>
        <name>五</name>
        <pose>Unspecified</pose>
        <truncated>0</truncated>
        <difficult>0</difficult>
        <bndbox>
            <xmin>1946</xmin>
            <ymin>1511</ymin>
            <xmax>2095</xmax>
            <ymax>1630</ymax>
        </bndbox>
    </object>
    <object>
        <name>卷</name>
        <pose>Unspecified</pose>
        <truncated>0</truncated>
        <difficult>0</difficult>
        <bndbox>
            <xmin>1938</xmin>
            <ymin>1636</ymin>
            <xmax>2114</xmax>
            <ymax>1796</ymax>
        </bndbox>
    </object>
    <object>
        <name>陳</name>
        <pose>Unspecified</pose>
        <truncated>0</truncated>
        <difficult>0</difficult>
        <bndbox>
            <xmin>1743</xmin>
            <ymin>897</ymin>
            <xmax>1915</xmax>
            <ymax>1063</ymax>
        </bndbox>
    </object>
    <object>
        <name>氏</name>
        <pose>Unspecified</pose>
        <truncated>0</truncated>
        <difficult>0</difficult>
        <bndbox>
            <xmin>1745</xmin>
            <ymin>1066</ymin>
            <xmax>1897</xmax>
            <ymax>1207</ymax>
        </bndbox>
    </object>
    <object>
        <name>曰</name>
        <pose>Unspecified</pose>
        <truncated>0</truncated>
        <difficult>0</difficult>
        <bndbox>
            <xmin>1752</xmin>
            <ymin>1215</ymin>
            <xmax>1886</xmax>
            <ymax>1354</ymax>
        </bndbox>
    </object>
    <object>
        <name>天</name>
        <pose>Unspecified</pose>
        <truncated>0</truncated>
        <difficult>0</difficult>
        <bndbox>
            <xmin>1743</xmin>
            <ymin>1364</ymin>
            <xmax>1900</xmax>
            <ymax>1501</ymax>
        </bndbox>
    </object>
    <object>
        <name>台</name>
        <pose>Unspecified</pose>
        <truncated>0</truncated>
        <difficult>0</difficult>
        <bndbox>
            <xmin>1747</xmin>
            <ymin>1505</ymin>
            <xmax>1886</xmax>
            <ymax>1644</ymax>
        </bndbox>
    </object>
    <object>
        <name>縣</name>
        <pose>Unspecified</pose>
        <truncated>0</truncated>
        <difficult>0</difficult>
        <bndbox>
            <xmin>1738</xmin>
            <ymin>1649</ymin>
            <xmax>1901</xmax>
            <ymax>1796</ymax>
        </bndbox>
    </object>
    <object>
        <name>令</name>
        <pose>Unspecified</pose>
        <truncated>0</truncated>
        <difficult>0</difficult>
        <bndbox>
            <xmin>1731</xmin>
            <ymin>1798</ymin>
            <xmax>1913</xmax>
            <ymax>1950</ymax>
        </bndbox>
    </object>
    <object>
        <name>南</name>
        <pose>Unspecified</pose>
        <truncated>0</truncated>
        <difficult>0</difficult>
        <bndbox>
            <xmin>1744</xmin>
            <ymin>1953</ymin>
            <xmax>1904</xmax>
            <ymax>2127</ymax>
        </bndbox>
    </object>
    <object>
        <name>城</name>
        <pose>Unspecified</pose>
        <truncated>0</truncated>
        <difficult>0</difficult>
        <bndbox>
            <xmin>1735</xmin>
            <ymin>2123</ymin>
            <xmax>1915</xmax>
            <ymax>2258</ymax>
        </bndbox>
    </object>
    <object>
        <name>王</name>
        <pose>Unspecified</pose>
        <truncated>0</truncated>
        <difficult>0</difficult>
        <bndbox>
            <xmin>1746</xmin>
            <ymin>2267</ymin>
            <xmax>1907</xmax>
            <ymax>2387</ymax>
        </bndbox>
    </object>
    <object>
        <name>無</name>
        <pose>Unspecified</pose>
        <truncated>0</truncated>
        <difficult>0</difficult>
        <bndbox>
            <xmin>1742</xmin>
            <ymin>2394</ymin>
            <xmax>1915</xmax>
            <ymax>2544</ymax>
        </bndbox>
    </object>
    <object>
        <name>咎</name>
        <pose>Unspecified</pose>
        <truncated>0</truncated>
        <difficult>0</difficult>
        <bndbox>
            <xmin>1742</xmin>
            <ymin>2548</ymin>
            <xmax>1900</xmax>
            <ymax>2692</ymax>
        </bndbox>
    </object>
    <object>
        <name>補</name>
        <pose>Unspecified</pose>
        <truncated>0</truncated>
        <difficult>0</difficult>
        <bndbox>
            <xmin>1744</xmin>
            <ymin>2695</ymin>
            <xmax>1899</xmax>
            <ymax>2843</ymax>
        </bndbox>
    </object>
    <object>
        <name>之</name>
        <pose>Unspecified</pose>
        <truncated>0</truncated>
        <difficult>0</difficult>
        <bndbox>
            <xmin>1748</xmin>
            <ymin>2857</ymin>
            <xmax>1900</xmax>
            <ymax>2978</ymax>
        </bndbox>
    </object>
    <object>
        <name>撰</name>
        <pose>Unspecified</pose>
        <truncated>0</truncated>
        <difficult>0</difficult>
        <bndbox>
            <xmin>1745</xmin>
            <ymin>2989</ymin>
            <xmax>1909</xmax>
            <ymax>3140</ymax>
        </bndbox>
    </object>
    <object>
        <name>無</name>
        <pose>Unspecified</pose>
        <truncated>0</truncated>
        <difficult>0</difficult>
        <bndbox>
            <xmin>1741</xmin>
            <ymin>3145</ymin>
            <xmax>1908</xmax>
            <ymax>3290</ymax>
        </bndbox>
    </object>
    <object>
        <name>咎</name>
        <pose>Unspecified</pose>
        <truncated>0</truncated>
        <difficult>0</difficult>
        <bndbox>
            <xmin>1736</xmin>
            <ymin>3293</ymin>
            <xmax>1897</xmax>
            <ymax>3449</ymax>
        </bndbox>
    </object>
    <object>
        <name>嘉</name>
        <pose>Unspecified</pose>
        <truncated>0</truncated>
        <difficult>0</difficult>
        <bndbox>
            <xmin>1738</xmin>
            <ymin>3466</ymin>
            <xmax>1900</xmax>
            <ymax>3597</ymax>
        </bndbox>
    </object>
    <object>
        <name>祐</name>
        <pose>Unspecified</pose>
        <truncated>0</truncated>
        <difficult>0</difficult>
        <bndbox>
            <xmin>1743</xmin>
            <ymin>3601</ymin>
            <xmax>1897</xmax>
            <ymax>3730</ymax>
        </bndbox>
    </object>
    <object>
        <name>二</name>
        <pose>Unspecified</pose>
        <truncated>0</truncated>
        <difficult>0</difficult>
        <bndbox>
            <xmin>1531</xmin>
            <ymin>936</ymin>
            <xmax>1686</xmax>
            <ymax>1038</ymax>
        </bndbox>
    </object>
    <object>
        <name>年</name>
        <pose>Unspecified</pose>
        <truncated>0</truncated>
        <difficult>0</difficult>
        <bndbox>
            <xmin>1544</xmin>
            <ymin>1051</ymin>
            <xmax>1690</xmax>
            <ymax>1203</ymax>
        </bndbox>
    </object>
    <object>
        <name>進</name>
        <pose>Unspecified</pose>
        <truncated>0</truncated>
        <difficult>0</difficult>
        <bndbox>
            <xmin>1539</xmin>
            <ymin>1207</ymin>
            <xmax>1697</xmax>
            <ymax>1354</ymax>
        </bndbox>
    </object>
    <object>
        <name>士</name>
        <pose>Unspecified</pose>
        <truncated>0</truncated>
        <difficult>0</difficult>
        <bndbox>
            <xmin>1532</xmin>
            <ymin>1363</ymin>
            <xmax>1689</xmax>
            <ymax>1484</ymax>
        </bndbox>
    </object>
    <object>
        <name>曽</name>
        <pose>Unspecified</pose>
        <truncated>0</truncated>
        <difficult>0</difficult>
        <bndbox>
            <xmin>1545</xmin>
            <ymin>1490</ymin>
            <xmax>1681</xmax>
            <ymax>1649</ymax>
        </bndbox>
    </object>
    <object>
        <name>鞏</name>
        <pose>Unspecified</pose>
        <truncated>0</truncated>
        <difficult>0</difficult>
        <bndbox>
            <xmin>1533</xmin>
            <ymin>1654</ymin>
            <xmax>1689</xmax>
            <ymax>1818</ymax>
        </bndbox>
    </object>
    <object>
        <name>之</name>
        <pose>Unspecified</pose>
        <truncated>0</truncated>
        <difficult>0</difficult>
        <bndbox>
            <xmin>1530</xmin>
            <ymin>1820</ymin>
            <xmax>1687</xmax>
            <ymax>1940</ymax>
        </bndbox>
    </object>
    <object>
        <name>妺</name>
        <pose>Unspecified</pose>
        <truncated>0</truncated>
        <difficult>0</difficult>
        <bndbox>
            <xmin>1529</xmin>
            <ymin>1952</ymin>
            <xmax>1703</xmax>
            <ymax>2096</ymax>
        </bndbox>
    </object>
    <object>
        <name>夫</name>
        <pose>Unspecified</pose>
        <truncated>0</truncated>
        <difficult>0</difficult>
        <bndbox>
            <xmin>1537</xmin>
            <ymin>2098</ymin>
            <xmax>1698</xmax>
            <ymax>2245</ymax>
        </bndbox>
    </object>
    <object>
        <name>從</name>
        <pose>Unspecified</pose>
        <truncated>0</truncated>
        <difficult>0</difficult>
        <bndbox>
            <xmin>1535</xmin>
            <ymin>2249</ymin>
            <xmax>1702</xmax>
            <ymax>2399</ymax>
        </bndbox>
    </object>
    <object>
        <name>王</name>
        <pose>Unspecified</pose>
        <truncated>0</truncated>
        <difficult>0</difficult>
        <bndbox>
            <xmin>1547</xmin>
            <ymin>2408</ymin>
            <xmax>1693</xmax>
            <ymax>2523</ymax>
        </bndbox>
    </object>
    <object>
        <name>安</name>
        <pose>Unspecified</pose>
        <truncated>0</truncated>
        <difficult>0</difficult>
        <bndbox>
            <xmin>1546</xmin>
            <ymin>2536</ymin>
            <xmax>1701</xmax>
            <ymax>2680</ymax>
        </bndbox>
    </object>
    <object>
        <name>石</name>
        <pose>Unspecified</pose>
        <truncated>0</truncated>
        <difficult>0</difficult>
        <bndbox>
            <xmin>1543</xmin>
            <ymin>2692</ymin>
            <xmax>1684</xmax>
            <ymax>2830</ymax>
        </bndbox>
    </object>
    <object>
        <name>遊</name>
        <pose>Unspecified</pose>
        <truncated>0</truncated>
        <difficult>0</difficult>
        <bndbox>
            <xmin>1545</xmin>
            <ymin>2832</ymin>
            <xmax>1699</xmax>
            <ymax>2981</ymax>
        </bndbox>
    </object>
    <object>
        <name>最</name>
        <pose>Unspecified</pose>
        <truncated>0</truncated>
        <difficult>0</difficult>
        <bndbox>
            <xmin>1544</xmin>
            <ymin>2986</ymin>
            <xmax>1699</xmax>
            <ymax>3142</ymax>
        </bndbox>
    </object>
    <object>
        <name>乆</name>
        <pose>Unspecified</pose>
        <truncated>0</truncated>
        <difficult>0</difficult>
        <bndbox>
            <xmin>1556</xmin>
            <ymin>3152</ymin>
            <xmax>1709</xmax>
            <ymax>3276</ymax>
        </bndbox>
    </object>
    <object>
        <name>將</name>
        <pose>Unspecified</pose>
        <truncated>0</truncated>
        <difficult>0</difficult>
        <bndbox>
            <xmin>1552</xmin>
            <ymin>3280</ymin>
            <xmax>1700</xmax>
            <ymax>3429</ymax>
        </bndbox>
    </object>
    <object>
        <name>用</name>
        <pose>Unspecified</pose>
        <truncated>0</truncated>
        <difficult>0</difficult>
        <bndbox>
            <xmin>1556</xmin>
            <ymin>3438</ymin>
            <xmax>1680</xmax>
            <ymax>3577</ymax>
        </bndbox>
    </object>
    <object>
        <name>為</name>
        <pose>Unspecified</pose>
        <truncated>0</truncated>
        <difficult>0</difficult>
        <bndbox>
            <xmin>1555</xmin>
            <ymin>3579</ymin>
            <xmax>1696</xmax>
            <ymax>3729</ymax>
        </bndbox>
    </object>
    <object>
        <name>國</name>
        <pose>Unspecified</pose>
        <truncated>0</truncated>
        <difficult>0</difficult>
        <bndbox>
            <xmin>1342</xmin>
            <ymin>923</ymin>
            <xmax>1485</xmax>
            <ymax>1066</ymax>
        </bndbox>
    </object>
    <object>
        <name>子</name>
        <pose>Unspecified</pose>
        <truncated>0</truncated>
        <difficult>0</difficult>
        <bndbox>
            <xmin>1338</xmin>
            <ymin>1067</ymin>
            <xmax>1489</xmax>
            <ymax>1196</ymax>
        </bndbox>
    </object>
    <object>
        <name>學</name>
        <pose>Unspecified</pose>
        <truncated>0</truncated>
        <difficult>0</difficult>
        <bndbox>
            <xmin>1341</xmin>
            <ymin>1200</ymin>
            <xmax>1491</xmax>
            <ymax>1362</ymax>
        </bndbox>
    </object>
    <object>
        <name>官</name>
        <pose>Unspecified</pose>
        <truncated>0</truncated>
        <difficult>0</difficult>
        <bndbox>
            <xmin>1343</xmin>
            <ymin>1367</ymin>
            <xmax>1490</xmax>
            <ymax>1508</ymax>
        </bndbox>
    </object>
    <object>
        <name>未</name>
        <pose>Unspecified</pose>
        <truncated>0</truncated>
        <difficult>0</difficult>
        <bndbox>
            <xmin>1347</xmin>
            <ymin>1507</ymin>
            <xmax>1509</xmax>
            <ymax>1656</ymax>
        </bndbox>
    </object>
    <object>
        <name>及</name>
        <pose>Unspecified</pose>
        <truncated>0</truncated>
        <difficult>0</difficult>
        <bndbox>
            <xmin>1344</xmin>
            <ymin>1660</ymin>
            <xmax>1502</xmax>
            <ymax>1788</ymax>
        </bndbox>
    </object>
    <object>
        <name>而</name>
        <pose>Unspecified</pose>
        <truncated>0</truncated>
        <difficult>0</difficult>
        <bndbox>
            <xmin>1357</xmin>
            <ymin>1811</ymin>
            <xmax>1490</xmax>
            <ymax>1928</ymax>
        </bndbox>
    </object>
    <object>
        <name>卒</name>
        <pose>Unspecified</pose>
        <truncated>0</truncated>
        <difficult>0</difficult>
        <bndbox>
            <xmin>1348</xmin>
            <ymin>1939</ymin>
            <xmax>1500</xmax>
            <ymax>2097</ymax>
        </bndbox>
    </object>
    <object>
        <name>為</name>
        <pose>Unspecified</pose>
        <truncated>0</truncated>
        <difficult>0</difficult>
        <bndbox>
            <xmin>1348</xmin>
            <ymin>2103</ymin>
            <xmax>1498</xmax>
            <ymax>2262</ymax>
        </bndbox>
    </object>
    <object>
        <name>之</name>
        <pose>Unspecified</pose>
        <truncated>0</truncated>
        <difficult>0</difficult>
        <bndbox>
            <xmin>1349</xmin>
            <ymin>2266</ymin>
            <xmax>1501</xmax>
            <ymax>2379</ymax>
        </bndbox>
    </object>
    <object>
        <name>誌</name>
        <pose>Unspecified</pose>
        <truncated>0</truncated>
        <difficult>0</difficult>
        <bndbox>
            <xmin>1351</xmin>
            <ymin>2391</ymin>
            <xmax>1511</xmax>
            <ymax>2532</ymax>
        </bndbox>
    </object>
    <object>
        <name>墓</name>
        <pose>Unspecified</pose>
        <truncated>0</truncated>
        <difficult>0</difficult>
        <bndbox>
            <xmin>1351</xmin>
            <ymin>2538</ymin>
            <xmax>1505</xmax>
            <ymax>2705</ymax>
        </bndbox>
    </object>
    <object>
        <name>曽</name>
        <pose>Unspecified</pose>
        <truncated>0</truncated>
        <difficult>0</difficult>
        <bndbox>
            <xmin>1361</xmin>
            <ymin>2707</ymin>
            <xmax>1496</xmax>
            <ymax>2853</ymax>
        </bndbox>
    </object>
    <object>
        <name>肇</name>
        <pose>Unspecified</pose>
        <truncated>0</truncated>
        <difficult>0</difficult>
        <bndbox>
            <xmin>1346</xmin>
            <ymin>2858</ymin>
            <xmax>1506</xmax>
            <ymax>3009</ymax>
        </bndbox>
    </object>
    <object>
        <name>序</name>
        <pose>Unspecified</pose>
        <truncated>0</truncated>
        <difficult>0</difficult>
        <bndbox>
            <xmin>1348</xmin>
            <ymin>3019</ymin>
            <xmax>1503</xmax>
            <ymax>3172</ymax>
        </bndbox>
    </object>
    <object>
        <name>其</name>
        <pose>Unspecified</pose>
        <truncated>0</truncated>
        <difficult>0</difficult>
        <bndbox>
            <xmin>1352</xmin>
            <ymin>3172</ymin>
            <xmax>1512</xmax>
            <ymax>3308</ymax>
        </bndbox>
    </object>
    <object>
        <name>集</name>
        <pose>Unspecified</pose>
        <truncated>0</truncated>
        <difficult>0</difficult>
        <bndbox>
            <xmin>1364</xmin>
            <ymin>3308</ymin>
            <xmax>1513</xmax>
            <ymax>3458</ymax>
        </bndbox>
    </object>
    <object>
        <name>云</name>
        <pose>Unspecified</pose>
        <truncated>0</truncated>
        <difficult>0</difficult>
        <bndbox>
            <xmin>1370</xmin>
            <ymin>3467</ymin>
            <xmax>1503</xmax>
            <ymax>3583</ymax>
        </bndbox>
    </object>
    <object>
        <name>二</name>
        <pose>Unspecified</pose>
        <truncated>0</truncated>
        <difficult>0</difficult>
        <bndbox>
            <xmin>1373</xmin>
            <ymin>3606</ymin>
            <xmax>1501</xmax>
            <ymax>3704</ymax>
        </bndbox>
    </object>
    <object>
        <name>十</name>
        <pose>Unspecified</pose>
        <truncated>0</truncated>
        <difficult>0</difficult>
        <bndbox>
            <xmin>1147</xmin>
            <ymin>923</ymin>
            <xmax>1288</xmax>
            <ymax>1052</ymax>
        </bndbox>
    </object>
    <object>
        <name>卷</name>
        <pose>Unspecified</pose>
        <truncated>0</truncated>
        <difficult>0</difficult>
        <bndbox>
            <xmin>1136</xmin>
            <ymin>1057</ymin>
            <xmax>1297</xmax>
            <ymax>1206</ymax>
        </bndbox>
    </object>
    <object>
        <name>今</name>
        <pose>Unspecified</pose>
        <truncated>0</truncated>
        <difficult>0</difficult>
        <bndbox>
            <xmin>1127</xmin>
            <ymin>1209</ymin>
            <xmax>1300</xmax>
            <ymax>1356</ymax>
        </bndbox>
    </object>
    <object>
        <name>惟</name>
        <pose>Unspecified</pose>
        <truncated>0</truncated>
        <difficult>0</difficult>
        <bndbox>
            <xmin>1136</xmin>
            <ymin>1358</ymin>
            <xmax>1295</xmax>
            <ymax>1504</ymax>
        </bndbox>
    </object>
    <object>
        <name>十</name>
        <pose>Unspecified</pose>
        <truncated>0</truncated>
        <difficult>0</difficult>
        <bndbox>
            <xmin>1140</xmin>
            <ymin>1511</ymin>
            <xmax>1295</xmax>
            <ymax>1642</ymax>
        </bndbox>
    </object>
    <object>
        <name>五</name>
        <pose>Unspecified</pose>
        <truncated>0</truncated>
        <difficult>0</difficult>
        <bndbox>
            <xmin>1142</xmin>
            <ymin>1658</ymin>
            <xmax>1301</xmax>
            <ymax>1770</ymax>
        </bndbox>
    </object>
    <object>
        <name>卷</name>
        <pose>Unspecified</pose>
        <truncated>0</truncated>
        <difficult>0</difficult>
        <bndbox>
            <xmin>1143</xmin>
            <ymin>1781</ymin>
            <xmax>1308</xmax>
            <ymax>1944</ymax>
        </bndbox>
    </object>
    <object>
        <name>南</name>
        <pose>Unspecified</pose>
        <truncated>0</truncated>
        <difficult>0</difficult>
        <bndbox>
            <xmin>939</xmin>
            <ymin>783</ymin>
            <xmax>1083</xmax>
            <ymax>921</ymax>
        </bndbox>
    </object>
    <object>
        <name>陽</name>
        <pose>Unspecified</pose>
        <truncated>0</truncated>
        <difficult>0</difficult>
        <bndbox>
            <xmin>942</xmin>
            <ymin>922</ymin>
            <xmax>1091</xmax>
            <ymax>1069</ymax>
        </bndbox>
    </object>
    <object>
        <name>集</name>
        <pose>Unspecified</pose>
        <truncated>0</truncated>
        <difficult>0</difficult>
        <bndbox>
            <xmin>934</xmin>
            <ymin>1070</ymin>
            <xmax>1089</xmax>
            <ymax>1230</ymax>
        </bndbox>
    </object>
    <object>
        <name>二</name>
        <pose>Unspecified</pose>
        <truncated>0</truncated>
        <difficult>0</difficult>
        <bndbox>
            <xmin>943</xmin>
            <ymin>1241</ymin>
            <xmax>1091</xmax>
            <ymax>1338</ymax>
        </bndbox>
    </object>
    <object>
        <name>十</name>
        <pose>Unspecified</pose>
        <truncated>0</truncated>
        <difficult>0</difficult>
        <bndbox>
            <xmin>947</xmin>
            <ymin>1355</ymin>
            <xmax>1089</xmax>
            <ymax>1497</ymax>
        </bndbox>
    </object>
    <object>
        <name>卷</name>
        <pose>Unspecified</pose>
        <truncated>0</truncated>
        <difficult>0</difficult>
        <bndbox>
            <xmin>936</xmin>
            <ymin>1498</ymin>
            <xmax>1100</xmax>
            <ymax>1656</ymax>
        </bndbox>
    </object>
    <object>
        <name>陳</name>
        <pose>Unspecified</pose>
        <truncated>0</truncated>
        <difficult>0</difficult>
        <bndbox>
            <xmin>767</xmin>
            <ymin>904</ymin>
            <xmax>907</xmax>
            <ymax>1063</ymax>
        </bndbox>
    </object>
    <object>
        <name>氏</name>
        <pose>Unspecified</pose>
        <truncated>0</truncated>
        <difficult>0</difficult>
        <bndbox>
            <xmin>762</xmin>
            <ymin>1069</ymin>
            <xmax>906</xmax>
            <ymax>1208</ymax>
        </bndbox>
    </object>
    <object>
        <name>曰</name>
        <pose>Unspecified</pose>
        <truncated>0</truncated>
        <difficult>0</difficult>
        <bndbox>
            <xmin>773</xmin>
            <ymin>1228</ymin>
            <xmax>915</xmax>
            <ymax>1347</ymax>
        </bndbox>
    </object>
    <object>
        <name>門</name>
        <pose>Unspecified</pose>
        <truncated>0</truncated>
        <difficult>0</difficult>
        <bndbox>
            <xmin>771</xmin>
            <ymin>1353</ymin>
            <xmax>911</xmax>
            <ymax>1498</ymax>
        </bndbox>
    </object>
    <object>
        <name>下</name>
        <pose>Unspecified</pose>
        <truncated>0</truncated>
        <difficult>0</difficult>
        <bndbox>
            <xmin>773</xmin>
            <ymin>1509</ymin>
            <xmax>908</xmax>
            <ymax>1645</ymax>
        </bndbox>
    </object>
    <object>
        <name>侍</name>
        <pose>Unspecified</pose>
        <truncated>0</truncated>
        <difficult>0</difficult>
        <bndbox>
            <xmin>767</xmin>
            <ymin>1651</ymin>
            <xmax>915</xmax>
            <ymax>1809</ymax>
        </bndbox>
    </object>
    <object>
        <name>郎</name>
        <pose>Unspecified</pose>
        <truncated>0</truncated>
        <difficult>0</difficult>
        <bndbox>
            <xmin>763</xmin>
            <ymin>1814</ymin>
            <xmax>919</xmax>
            <ymax>1965</ymax>
        </bndbox>
    </object>
    <object>
        <name>頴</name>
        <pose>Unspecified</pose>
        <truncated>0</truncated>
        <difficult>0</difficult>
        <bndbox>
            <xmin>759</xmin>
            <ymin>1967</ymin>
            <xmax>912</xmax>
            <ymax>2111</ymax>
        </bndbox>
    </object>
    <object>
        <name>昌</name>
        <pose>Unspecified</pose>
        <truncated>0</truncated>
        <difficult>0</difficult>
        <bndbox>
            <xmin>771</xmin>
            <ymin>2118</ymin>
            <xmax>903</xmax>
            <ymax>2255</ymax>
        </bndbox>
    </object>
    <object>
        <name>韓</name>
        <pose>Unspecified</pose>
        <truncated>0</truncated>
        <difficult>0</difficult>
        <bndbox>
            <xmin>758</xmin>
            <ymin>2259</ymin>
            <xmax>917</xmax>
            <ymax>2415</ymax>
        </bndbox>
    </object>
    <object>
        <name>維</name>
        <pose>Unspecified</pose>
        <truncated>0</truncated>
        <difficult>0</difficult>
        <bndbox>
            <xmin>759</xmin>
            <ymin>2416</ymin>
            <xmax>917</xmax>
            <ymax>2548</ymax>
        </bndbox>
    </object>
    <object>
        <name>持</name>
        <pose>Unspecified</pose>
        <truncated>0</truncated>
        <difficult>0</difficult>
        <bndbox>
            <xmin>766</xmin>
            <ymin>2550</ymin>
            <xmax>917</xmax>
            <ymax>2699</ymax>
        </bndbox>
    </object>
    <object>
        <name>國</name>
        <pose>Unspecified</pose>
        <truncated>0</truncated>
        <difficult>0</difficult>
        <bndbox>
            <xmin>777</xmin>
            <ymin>2703</ymin>
            <xmax>912</xmax>
            <ymax>2840</ymax>
        </bndbox>
    </object>
    <object>
        <name>撰</name>
        <pose>Unspecified</pose>
        <truncated>0</truncated>
        <difficult>0</difficult>
        <bndbox>
            <xmin>764</xmin>
            <ymin>2850</ymin>
            <xmax>931</xmax>
            <ymax>2991</ymax>
        </bndbox>
    </object>
    <object>
        <name>封</name>
        <pose>Unspecified</pose>
        <truncated>0</truncated>
        <difficult>0</difficult>
        <bndbox>
            <xmin>765</xmin>
            <ymin>2994</ymin>
            <xmax>928</xmax>
            <ymax>3140</ymax>
        </bndbox>
    </object>
    <object>
        <name>南</name>
        <pose>Unspecified</pose>
        <truncated>0</truncated>
        <difficult>0</difficult>
        <bndbox>
            <xmin>777</xmin>
            <ymin>3145</ymin>
            <xmax>911</xmax>
            <ymax>3293</ymax>
        </bndbox>
    </object>
    <object>
        <name>陽</name>
        <pose>Unspecified</pose>
        <truncated>0</truncated>
        <difficult>0</difficult>
        <bndbox>
            <xmin>769</xmin>
            <ymin>3294</ymin>
            <xmax>918</xmax>
            <ymax>3444</ymax>
        </bndbox>
    </object>
    <object>
        <name>郡</name>
        <pose>Unspecified</pose>
        <truncated>0</truncated>
        <difficult>0</difficult>
        <bndbox>
            <xmin>760</xmin>
            <ymin>3448</ymin>
            <xmax>922</xmax>
            <ymax>3595</ymax>
        </bndbox>
    </object>
    <object>
        <name>公</name>
        <pose>Unspecified</pose>
        <truncated>0</truncated>
        <difficult>0</difficult>
        <bndbox>
            <xmin>773</xmin>
            <ymin>3612</ymin>
            <xmax>927</xmax>
            <ymax>3740</ymax>
        </bndbox>
    </object>
    <object>
        <name>故</name>
        <pose>Unspecified</pose>
        <truncated>0</truncated>
        <difficult>0</difficult>
        <bndbox>
            <xmin>563</xmin>
            <ymin>910</ymin>
            <xmax>721</xmax>
            <ymax>1059</ymax>
        </bndbox>
    </object>
    <object>
        <name>以</name>
        <pose>Unspecified</pose>
        <truncated>0</truncated>
        <difficult>0</difficult>
        <bndbox>
            <xmin>556</xmin>
            <ymin>1083</ymin>
            <xmax>714</xmax>
            <ymax>1200</ymax>
        </bndbox>
    </object>
    <object>
        <name>名</name>
        <pose>Unspecified</pose>
        <truncated>0</truncated>
        <difficult>0</difficult>
        <bndbox>
            <xmin>556</xmin>
            <ymin>1210</ymin>
            <xmax>695</xmax>
            <ymax>1354</ymax>
        </bndbox>
    </object>
    <object>
        <name>集</name>
        <pose>Unspecified</pose>
        <truncated>0</truncated>
        <difficult>0</difficult>
        <bndbox>
            <xmin>555</xmin>
            <ymin>1359</ymin>
            <xmax>711</xmax>
            <ymax>1520</ymax>
        </bndbox>
    </object>
    <object>
        <name>沈</name>
        <pose>Unspecified</pose>
        <truncated>0</truncated>
        <difficult>0</difficult>
        <bndbox>
            <xmin>564</xmin>
            <ymin>1522</ymin>
            <xmax>731</xmax>
            <ymax>1651</ymax>
        </bndbox>
    </object>
    <object>
        <name>晦</name>
        <pose>Unspecified</pose>
        <truncated>0</truncated>
        <difficult>0</difficult>
        <bndbox>
            <xmin>565</xmin>
            <ymin>1653</ymin>
            <xmax>730</xmax>
            <ymax>1823</ymax>
        </bndbox>
    </object>
    <object>
        <name>元</name>
        <pose>Unspecified</pose>
        <truncated>0</truncated>
        <difficult>0</difficult>
        <bndbox>
            <xmin>557</xmin>
            <ymin>1827</ymin>
            <xmax>706</xmax>
            <ymax>1962</ymax>
        </bndbox>
    </object>
    <object>
        <name>用</name>
        <pose>Unspecified</pose>
        <truncated>0</truncated>
        <difficult>0</difficult>
        <bndbox>
            <xmin>569</xmin>
            <ymin>1965</ymin>
            <xmax>708</xmax>
            <ymax>2107</ymax>
        </bndbox>
    </object>
    <object>
        <name>其</name>
        <pose>Unspecified</pose>
        <truncated>0</truncated>
        <difficult>0</difficult>
        <bndbox>
            <xmin>565</xmin>
            <ymin>2109</ymin>
            <xmax>734</xmax>
            <ymax>2264</ymax>
        </bndbox>
    </object>
    <object>
        <name>外</name>
        <pose>Unspecified</pose>
        <truncated>0</truncated>
        <difficult>0</difficult>
        <bndbox>
            <xmin>561</xmin>
            <ymin>2264</ymin>
            <xmax>735</xmax>
            <ymax>2409</ymax>
        </bndbox>
    </object>
    <object>
        <name>孫</name>
        <pose>Unspecified</pose>
        <truncated>0</truncated>
        <difficult>0</difficult>
        <bndbox>
            <xmin>567</xmin>
            <ymin>2411</ymin>
            <xmax>727</xmax>
            <ymax>2554</ymax>
        </bndbox>
    </object>
    <object>
        <name>也</name>
        <pose>Unspecified</pose>
        <truncated>0</truncated>
        <difficult>0</difficult>
        <bndbox>
            <xmin>557</xmin>
            <ymin>2563</ymin>
            <xmax>695</xmax>
            <ymax>2686</ymax>
        </bndbox>
    </object>
    <object>
        <name>卷</name>
        <pose>Unspecified</pose>
        <truncated>0</truncated>
        <difficult>0</difficult>
        <bndbox>
            <xmin>578</xmin>
            <ymin>2692</ymin>
            <xmax>736</xmax>
            <ymax>2848</ymax>
        </bndbox>
    </object>
    <object>
        <name>首</name>
        <pose>Unspecified</pose>
        <truncated>0</truncated>
        <difficult>0</difficult>
        <bndbox>
            <xmin>580</xmin>
            <ymin>2856</ymin>
            <xmax>723</xmax>
            <ymax>2994</ymax>
        </bndbox>
    </object>
    <object>
        <name>載</name>
        <pose>Unspecified</pose>
        <truncated>0</truncated>
        <difficult>0</difficult>
        <bndbox>
            <xmin>578</xmin>
            <ymin>3004</ymin>
            <xmax>734</xmax>
            <ymax>3159</ymax>
        </bndbox>
    </object>
    <object>
        <name>鮮</name>
        <pose>Unspecified</pose>
        <truncated>0</truncated>
        <difficult>0</difficult>
        <bndbox>
            <xmin>579</xmin>
            <ymin>3163</ymin>
            <xmax>733</xmax>
            <ymax>3307</ymax>
        </bndbox>
    </object>
    <object>
        <name>干</name>
        <pose>Unspecified</pose>
        <truncated>0</truncated>
        <difficult>0</difficult>
        <bndbox>
            <xmin>583</xmin>
            <ymin>3312</ymin>
            <xmax>719</xmax>
            <ymax>3431</ymax>
        </bndbox>
    </object>
    <object>
        <name>綽</name>
        <pose>Unspecified</pose>
        <truncated>0</truncated>
        <difficult>0</difficult>
        <bndbox>
            <xmin>575</xmin>
            <ymin>3447</ymin>
            <xmax>740</xmax>
            <ymax>3600</ymax>
        </bndbox>
    </object>
    <object>
        <name>所</name>
        <pose>Unspecified</pose>
        <truncated>0</truncated>
        <difficult>0</difficult>
        <bndbox>
            <xmin>577</xmin>
            <ymin>3603</ymin>
            <xmax>734</xmax>
            <ymax>3742</ymax>
        </bndbox>
    </object>
    <object>
        <name>述</name>
        <pose>Unspecified</pose>
        <truncated>0</truncated>
        <difficult>0</difficult>
        <bndbox>
            <xmin>356</xmin>
            <ymin>916</ymin>
            <xmax>498</xmax>
            <ymax>1063</ymax>
        </bndbox>
    </object>
    <object>
        <name>行</name>
        <pose>Unspecified</pose>
        <truncated>0</truncated>
        <difficult>0</difficult>
        <bndbox>
            <xmin>369</xmin>
            <ymin>1075</ymin>
            <xmax>516</xmax>
            <ymax>1210</ymax>
        </bndbox>
    </object>
    <object>
        <name>状</name>
        <pose>Unspecified</pose>
        <truncated>0</truncated>
        <difficult>0</difficult>
        <bndbox>
            <xmin>362</xmin>
            <ymin>1213</ymin>
            <xmax>527</xmax>
            <ymax>1357</ymax>
        </bndbox>
    </object>
    <object>
        <name>而</name>
        <pose>Unspecified</pose>
        <truncated>0</truncated>
        <difficult>0</difficult>
        <bndbox>
            <xmin>370</xmin>
            <ymin>1368</ymin>
            <xmax>519</xmax>
            <ymax>1498</ymax>
        </bndbox>
    </object>
    <object>
        <name>晦</name>
        <pose>Unspecified</pose>
        <truncated>0</truncated>
        <difficult>0</difficult>
        <bndbox>
            <xmin>370</xmin>
            <ymin>1514</ymin>
            <xmax>528</xmax>
            <ymax>1657</ymax>
        </bndbox>
    </object>
    <object>
        <name>䟦</name>
        <pose>Unspecified</pose>
        <truncated>0</truncated>
        <difficult>0</difficult>
        <bndbox>
            <xmin>371</xmin>
            <ymin>1666</ymin>
            <xmax>539</xmax>
            <ymax>1805</ymax>
        </bndbox>
    </object>
    <object>
        <name>其</name>
        <pose>Unspecified</pose>
        <truncated>0</truncated>
        <difficult>0</difficult>
        <bndbox>
            <xmin>373</xmin>
            <ymin>1808</ymin>
            <xmax>531</xmax>
            <ymax>1962</ymax>
        </bndbox>
    </object>
    <object>
        <name>後</name>
        <pose>Unspecified</pose>
        <truncated>0</truncated>
        <difficult>0</difficult>
        <bndbox>
            <xmin>376</xmin>
            <ymin>1967</ymin>
            <xmax>523</xmax>
            <ymax>2111</ymax>
        </bndbox>
    </object>
    <object>
        <name>南</name>
        <pose>Unspecified</pose>
        <truncated>0</truncated>
        <difficult>0</difficult>
        <bndbox>
            <xmin>378</xmin>
            <ymin>2114</ymin>
            <xmax>531</xmax>
            <ymax>2262</ymax>
        </bndbox>
    </object>
    <object>
        <name>潤</name>
        <pose>Unspecified</pose>
        <truncated>0</truncated>
        <difficult>0</difficult>
        <bndbox>
            <xmin>375</xmin>
            <ymin>2264</ymin>
            <xmax>526</xmax>
            <ymax>2405</ymax>
        </bndbox>
    </object>
    <object>
        <name>元</name>
        <pose>Unspecified</pose>
        <truncated>0</truncated>
        <difficult>0</difficult>
        <bndbox>
            <xmin>373</xmin>
            <ymin>2411</ymin>
            <xmax>536</xmax>
            <ymax>2548</ymax>
        </bndbox>
    </object>
    <object>
        <name>吉</name>
        <pose>Unspecified</pose>
        <truncated>0</truncated>
        <difficult>0</difficult>
        <bndbox>
            <xmin>390</xmin>
            <ymin>2551</ymin>
            <xmax>526</xmax>
            <ymax>2691</ymax>
        </bndbox>
    </object>
    <object>
        <name>無</name>
        <pose>Unspecified</pose>
        <truncated>0</truncated>
        <difficult>0</difficult>
        <bndbox>
            <xmin>373</xmin>
            <ymin>2698</ymin>
            <xmax>537</xmax>
            <ymax>2853</ymax>
        </bndbox>
    </object>
    <object>
        <name>咎</name>
        <pose>Unspecified</pose>
        <truncated>0</truncated>
        <difficult>0</difficult>
        <bndbox>
            <xmin>373</xmin>
            <ymin>2860</ymin>
            <xmax>534</xmax>
            <ymax>3006</ymax>
        </bndbox>
    </object>
    <object>
        <name>其</name>
        <pose>Unspecified</pose>
        <truncated>0</truncated>
        <difficult>0</difficult>
        <bndbox>
            <xmin>374</xmin>
            <ymin>3011</ymin>
            <xmax>539</xmax>
            <ymax>3158</ymax>
        </bndbox>
    </object>
    <object>
        <name>四</name>
        <pose>Unspecified</pose>
        <truncated>0</truncated>
        <difficult>0</difficult>
        <bndbox>
            <xmin>389</xmin>
            <ymin>3172</ymin>
            <xmax>534</xmax>
            <ymax>3279</ymax>
        </bndbox>
    </object>
    <object>
        <name>世</name>
        <pose>Unspecified</pose>
        <truncated>0</truncated>
        <difficult>0</difficult>
        <bndbox>
            <xmin>389</xmin>
            <ymin>3291</ymin>
            <xmax>538</xmax>
            <ymax>3416</ymax>
        </bndbox>
    </object>
    <object>
        <name>孫</name>
        <pose>Unspecified</pose>
        <truncated>0</truncated>
        <difficult>0</difficult>
        <bndbox>
            <xmin>382</xmin>
            <ymin>3428</ymin>
            <xmax>534</xmax>
            <ymax>3594</ymax>
        </bndbox>
    </object>
    <object>
        <name>無</name>
        <pose>Unspecified</pose>
        <truncated>0</truncated>
        <difficult>0</difficult>
        <bndbox>
            <xmin>162</xmin>
            <ymin>785</ymin>
            <xmax>321</xmax>
            <ymax>940</ymax>
        </bndbox>
    </object>
    <object>
        <name>為</name>
        <pose>Unspecified</pose>
        <truncated>0</truncated>
        <difficult>0</difficult>
        <bndbox>
            <xmin>166</xmin>
            <ymin>941</ymin>
            <xmax>315</xmax>
            <ymax>1074</ymax>
        </bndbox>
    </object>
    <object>
        <name>集</name>
        <pose>Unspecified</pose>
        <truncated>0</truncated>
        <difficult>0</difficult>
        <bndbox>
            <xmin>163</xmin>
            <ymin>1077</ymin>
            <xmax>322</xmax>
            <ymax>1233</ymax>
        </bndbox>
    </object>
    <object>
        <name>十</name>
        <pose>Unspecified</pose>
        <truncated>0</truncated>
        <difficult>0</difficult>
        <bndbox>
            <xmin>170</xmin>
            <ymin>1238</ymin>
            <xmax>322</xmax>
            <ymax>1357</ymax>
        </bndbox>
    </object>
    <object>
        <name>五</name>
        <pose>Unspecified</pose>
        <truncated>0</truncated>
        <difficult>0</difficult>
        <bndbox>
            <xmin>178</xmin>
            <ymin>1372</ymin>
            <xmax>329</xmax>
            <ymax>1487</ymax>
        </bndbox>
    </object>
    <object>
        <name>卷</name>
        <pose>Unspecified</pose>
        <truncated>0</truncated>
        <difficult>0</difficult>
        <bndbox>
            <xmin>168</xmin>
            <ymin>1500</ymin>
            <xmax>323</xmax>
            <ymax>1660</ymax>
        </bndbox>
    </object>
    <object>
        <name>别</name>
        <pose>Unspecified</pose>
        <truncated>0</truncated>
        <difficult>0</difficult>
        <bndbox>
            <xmin>169</xmin>
            <ymin>1664</ymin>
            <xmax>316</xmax>
            <ymax>1808</ymax>
        </bndbox>
    </object>
    <object>
        <name>集</name>
        <pose>Unspecified</pose>
        <truncated>0</truncated>
        <difficult>0</difficult>
        <bndbox>
            <xmin>174</xmin>
            <ymin>1807</ymin>
            <xmax>332</xmax>
            <ymax>1972</ymax>
        </bndbox>
    </object>
    <object>
        <name>十</name>
        <pose>Unspecified</pose>
        <truncated>0</truncated>
        <difficult>0</difficult>
        <bndbox>
            <xmin>180</xmin>
            <ymin>1980</ymin>
            <xmax>324</xmax>
            <ymax>2109</ymax>
        </bndbox>
    </object>
    <object>
        <name>卷</name>
        <pose>Unspecified</pose>
        <truncated>0</truncated>
        <difficult>0</difficult>
        <bndbox>
            <xmin>171</xmin>
            <ymin>2113</ymin>
            <xmax>335</xmax>
            <ymax>2278</ymax>
        </bndbox>
    </object>
    <object>
        <name>敝</name>
        <pose>Unspecified</pose>
        <truncated>0</truncated>
        <difficult>0</difficult>
        <bndbox>
            <xmin>12</xmin>
            <ymin>1513</ymin>
            <xmax>121</xmax>
            <ymax>1636</ymax>
        </bndbox>
    </object>
    <object>
        <name>䭾</name>
        <pose>Unspecified</pose>
        <truncated>0</truncated>
        <difficult>0</difficult>
        <bndbox>
            <xmin>17</xmin>
            <ymin>1637</ymin>
            <xmax>120</xmax>
            <ymax>1740</ymax>
        </bndbox>
    </object>
    <object>
        <name>通</name>
        <pose>Unspecified</pose>
        <truncated>0</truncated>
        <difficult>0</difficult>
        <bndbox>
            <xmin>19</xmin>
            <ymin>1743</ymin>
            <xmax>118</xmax>
            <ymax>1857</ymax>
        </bndbox>
    </object>
    <object>
        <name>當</name>
        <pose>Unspecified</pose>
        <truncated>0</truncated>
        <difficult>0</difficult>
        <bndbox>
            <xmin>15</xmin>
            <ymin>1850</ymin>
            <xmax>117</xmax>
            <ymax>1972</ymax>
        </bndbox>
    </object>
</annotation>
